Workbook

Sheet README
A1: Purse Maison – Mock Historical Data (from client catalog)
A2: Built from the client's Sample_Data.xlsx (1,525 items). Client allowed it to be used and modified as mock history.
A4: What is REAL (from the client file)
A5: Barcode, brand, full item name, price. Model, colour, hardware, date code/stamp and size are parsed from the item name.
A6: What is GENERATED (mock) – shaded cream in every sheet
A7: All dates, consignors, buyers, condition notes, accessories, inquiry channel, sale type, layaway payments, and which items sold.
A8: Consignor and buyer names are fictional; emails use example.com and phone numbers are random.
A10: How the data is split
A11: Sold Items – past sales from Oct 2023 to Oct 13, 2026 (36 full months + October so far), imported as full item + listing + sale records.
A12: Current Stock – items listed now (Available) or on an active layaway (Reserved).
A13: Closed Items – rejected or failed authentication, never listed.
A14: Historical Sales – sales of items priced in the markup-rule gap (₱20,001–₱49,999, or ₱49,001–₱49,999 for shoes/wallets).
... A38: Excluded (no price): 1

Sheet Monthly Summary
A1: Month | B1: Full-Record Sales (count) | C1: Full-Record Revenue | D1: Historical Sales (count) | E1: Historical Revenue | F1: Total Revenue
A2: 45200 | B2: =COUNTIFS('Sold Items'!$R$2:$R$720,">="&A2,'Sold Items'!$R$2:$R$720,"<"&EDATE(A2,1)) -> 12 | C2: =SUMIFS('Sold Items'!$H$2:$H$720,'Sold Items'!$R$2:$R$720,">="&A2,'Sold Items'!$R$2:$R$720,"<"&EDATE(A2,1)) -> 1808600 | D2: =COUNTIFS('Historical Sales'!$A$2:$A$243,">="&A2,'Historical Sales'!$A$2:$A$243,"<"&EDATE(A2,1)) -> 2 | E2: =SUMIFS('Historical Sales'!$F$2:$F$243,'Historical Sales'!$A$2:$A$243,">="&A2,'Historical Sales'!$A$2:$A$243,"<"&EDATE(A2,1)) -> 82600 | F2: =C2+E2 -> 1891200
A3: 45231 | B3: =COUNTIFS('Sold Items'!$R$2:$R$720,">="&A3,'Sold Items'!$R$2:$R$720,"<"&EDATE(A3,1)) -> 15 | C3: =SUMIFS('Sold Items'!$H$2:$H$720,'Sold Items'!$R$2:$R$720,">="&A3,'Sold Items'!$R$2:$R$720,"<"&EDATE(A3,1)) -> 2189300 | D3: =COUNTIFS('Historical Sales'!$A$2:$A$243,">="&A3,'Historical Sales'!$A$2:$A$243,"<"&EDATE(A3,1)) -> 3 | E3: =SUMIFS('Historical Sales'!$F$2:$F$243,'Historical Sales'!$A$2:$A$243,">="&A3,'Historical Sales'!$A$2:$A$243,"<"&EDATE(A3,1)) -> 94100 | F3: =C3+E3 -> 2283400
A4: 45261 | B4: =COUNTIFS('Sold Items'!$R$2:$R$720,">="&A4,'Sold Items'!$R$2:$R$720,"<"&EDATE(A4,1)) -> 28 | C4: =SUMIFS('Sold Items'!$H$2:$H$720,'Sold Items'!$R$2:$R$720,">="&A4,'Sold Items'!$R$2:$R$720,"<"&EDATE(A4,1)) -> 3737900 | D4: =COUNTIFS('Historical Sales'!$A$2:$A$243,">="&A4,'Historical Sales'!$A$2:$A$243,"<"&EDATE(A4,1)) -> 8 | E4: =SUMIFS('Historical Sales'!$F$2:$F$243,'Historical Sales'!$A$2:$A$243,">="&A4,'Historical Sales'!$A$2:$A$243,"<"&EDATE(A4,1)) -> 311600 | F4: =C4+E4 -> 4049500
A5: 45292 | B5: =COUNTIFS('Sold Items'!$R$2:$R$720,">="&A5,'Sold Items'!$R$2:$R$720,"<"&EDATE(A5,1)) -> 18 | C5: =SUMIFS('Sold Items'!$H$2:$H$720,'Sold Items'!$R$2:$R$720,">="&A5,'Sold Items'!$R$2:$R$720,"<"&EDATE(A5,1)) -> 2628800 | D5: =COUNTIFS('Historical Sales'!$A$2:$A$243,">="&A5,'Historical Sales'!$A$2:$A$243,"<"&EDATE(A5,1)) -> 3 | E5: =SUMIFS('Historical Sales'!$F$2:$F$243,'Historical Sales'!$A$2:$A$243,">="&A5,'Historical Sales'!$A$2:$A$243,"<"&EDATE(A5,1)) -> 117500 | F5: =C5+E5 -> 2746300
A6: 45323 | B6: =COUNTIFS('Sold Items'!$R$2:$R$720,">="&A6,'Sold Items'!$R$2:$R$720,"<"&EDATE(A6,1)) -> 13 | C6: =SUMIFS('Sold Items'!$H$2:$H$720,'Sold Items'!$R$2:$R$720,">="&A6,'Sold Items'!$R$2:$R$720,"<"&EDATE(A6,1)) -> 1957400 | D6: =COUNTIFS('Historical Sales'!$A$2:$A$243,">="&A6,'Historical Sales'!$A$2:$A$243,"<"&EDATE(A6,1)) -> 4 | E6: =SUMIFS('Historical Sales'!$F$2:$F$243,'Historical Sales'!$A$2:$A$243,">="&A6,'Historical Sales'!$A$2:$A$243,"<"&EDATE(A6,1)) -> 158400 | F6: =C6+E6 -> 2115800
A7: 45352 | B7: =COUNTIFS('Sold Items'!$R$2:$R$720,">="&A7,'Sold Items'!$R$2:$R$720,"<"&EDATE(A7,1)) -> 17 | C7: =SUMIFS('Sold Items'!$H$2:$H$720,'Sold Items'!$R$2:$R$720,">="&A7,'Sold Items'!$R$2:$R$720,"<"&EDATE(A7,1)) -> 2956400 | D7: =COUNTIFS('Historical Sales'!$A$2:$A$243,">="&A7,'Historical Sales'!$A$2:$A$243,"<"&EDATE(A7,1)) -> 6 | E7: =SUMIFS('Historical Sales'!$F$2:$F$243,'Historical Sales'!$A$2:$A$243,">="&A7,'Historical Sales'!$A$2:$A$243,"<"&EDATE(A7,1)) -> 213300 | F7: =C7+E7 -> 3169700
A8: 45383 | B8: =COUNTIFS('Sold Items'!$R$2:$R$720,">="&A8,'Sold Items'!$R$2:$R$720,"<"&EDATE(A8,1)) -> 15 | C8: =SUMIFS('Sold Items'!$H$2:$H$720,'Sold Items'!$R$2:$R$720,">="&A8,'Sold Items'!$R$2:$R$720,"<"&EDATE(A8,1)) -> 2406700 | D8: =COUNTIFS('Historical Sales'!$A$2:$A$243,">="&A8,'Historical Sales'!$A$2:$A$243,"<"&EDATE(A8,1)) -> 5 | E8: =SUMIFS('Historical Sales'!$F$2:$F$243,'Historical Sales'!$A$2:$A$243,">="&A8,'Historical Sales'!$A$2:$A$243,"<"&EDATE(A8,1)) -> 178900 | F8: =C8+E8 -> 2585600
A9: 45413 | B9: =COUNTIFS('Sold Items'!$R$2:$R$720,">="&A9,'Sold Items'!$R$2:$R$720,"<"&EDATE(A9,1)) -> 12 | C9: =SUMIFS('Sold Items'!$H$2:$H$720,'Sold Items'!$R$2:$R$720,">="&A9,'Sold Items'!$R$2:$R$720,"<"&EDATE(A9,1)) -> 2079000 | D9: =COUNTIFS('Historical Sales'!$A$2:$A$243,">="&A9,'Historical Sales'!$A$2:$A$243,"<"&EDATE(A9,1)) -> 10 | E9: =SUMIFS('Historical Sales'!$F$2:$F$243,'Historical Sales'!$A$2:$A$243,">="&A9,'Historical Sales'!$A$2:$A$243,"<"&EDATE(A9,1)) -> 321000 | F9: =C9+E9 -> 2400000
A10: 45444 | B10: =COUNTIFS('Sold Items'!$R$2:$R$720,">="&A10,'Sold Items'!$R$2:$R$720,"<"&EDATE(A10,1)) -> 15 | C10: =SUMIFS('Sold Items'!$H$2:$H$720,'Sold Items'!$R$2:$R$720,">="&A10,'Sold Items'!$R$2:$R$720,"<"&EDATE(A10,1)) -> 2690300 | D10: =COUNTIFS('Historical Sales'!$A$2:$A$243,">="&A10,'Historical Sales'!$A$2:$A$243,"<"&EDATE(A10,1)) -> 5 | E10: =SUMIFS('Historical Sales'!$F$2:$F$243,'Historical Sales'!$A$2:$A$243,">="&A10,'Historical Sales'!$A$2:$A$243,"<"&EDATE(A10,1)) -> 144700 | F10: =C10+E10 -> 2835000
A11: 45474 | B11: =COUNTIFS('Sold Items'!$R$2:$R$720,">="&A11,'Sold Items'!$R$2:$R$720,"<"&EDATE(A11,1)) -> 12 | C11: =SUMIFS('Sold Items'!$H$2:$H$720,'Sold Items'!$R$2:$R$720,">="&A11,'Sold Items'!$R$2:$R$720,"<"&EDATE(A11,1)) -> 2308200 | D11: =COUNTIFS('Historical Sales'!$A$2:$A$243,">="&A11,'Historical Sales'!$A$2:$A$243,"<"&EDATE(A11,1)) -> 9 | E11: =SUMIFS('Historical Sales'!$F$2:$F$243,'Historical Sales'!$A$2:$A$243,">="&A11,'Historical Sales'!$A$2:$A$243,"<"&EDATE(A11,1)) -> 313700 | F11: =C11+E11 -> 2621900
A12: 45505 | B12: =COUNTIFS('Sold Items'!$R$2:$R$720,">="&A12,'Sold Items'!$R$2:$R$720,"<"&EDATE(A12,1)) -> 12 | C12: =SUMIFS('Sold Items'!$H$2:$H$720,'Sold Items'!$R$2:$R$720,">="&A12,'Sold Items'!$R$2:$R$720,"<"&EDATE(A12,1)) -> 1528500 | D12: =COUNTIFS('Historical Sales'!$A$2:$A$243,">="&A12,'Historical Sales'!$A$2:$A$243,"<"&EDATE(A12,1)) -> 5 | E12: =SUMIFS('Historical Sales'!$F$2:$F$243,'Historical Sales'!$A$2:$A$243,">="&A12,'Historical Sales'!$A$2:$A$243,"<"&EDATE(A12,1)) -> 185800 | F12: =C12+E12 -> 1714300
A13: 45536 | B13: =COUNTIFS('Sold Items'!$R$2:$R$720,">="&A13,'Sold Items'!$R$2:$R$720,"<"&EDATE(A13,1)) -> 20 | C13: =SUMIFS('Sold Items'!$H$2:$H$720,'Sold Items'!$R$2:$R$720,">="&A13,'Sold Items'!$R$2:$R$720,"<"&EDATE(A13,1)) -> 2589200 | D13: =COUNTIFS('Historical Sales'!$A$2:$A$243,">="&A13,'Historical Sales'!$A$2:$A$243,"<"&EDATE(A13,1)) -> 4 | E13: =SUMIFS('Historical Sales'!$F$2:$F$243,'Historical Sales'!$A$2:$A$243,">="&A13,'Historical Sales'!$A$2:$A$243,"<"&EDATE(A13,1)) -> 167800 | F13: =C13+E13 -> 2757000
... A38: 46296 | B38: =COUNTIFS('Sold Items'!$R$2:$R$720,">="&A38,'Sold Items'!$R$2:$R$720,"<"&EDATE(A38,1)) -> 9 | C38: =SUMIFS('Sold Items'!$H$2:$H$720,'Sold Items'!$R$2:$R$720,">="&A38,'Sold Items'!$R$2:$R$720,"<"&EDATE(A38,1)) -> 1837500 | D38: =COUNTIFS('Historical Sales'!$A$2:$A$243,">="&A38,'Historical Sales'!$A$2:$A$243,"<"&EDATE(A38,1)) -> 3 | E38: =SUMIFS('Historical Sales'!$F$2:$F$243,'Historical Sales'!$A$2:$A$243,">="&A38,'Historical Sales'!$A$2:$A$243,"<"&EDATE(A38,1)) -> 116100 | F38: =C38+E38 -> 1953600
A39: Total | B39: =SUM(B2:B38) -> 719 | C39: =SUM(C2:C38) -> 126164900 | D39: =SUM(D2:D38) -> 242 | E39: =SUM(E2:E38) -> 8707300 | F39: =SUM(F2:F38) -> 134872200
A41: Full-record revenue counts sales by Sold At date. Layaways still being paid are excluded (not verified yet). October 2026 is month-to-date (up to Oct 13).

Sheet Sold Items
A1: Barcode | B1: Brand | C1: Model | D1: Category | E1: Colour / Material | F1: Hardware | G1: Date Code | H1: Price | I1: Markup | J1: Consignor Payout | K1: Consignor | L1: Condition | M1: Accessories | N1: Inquiry Channel | O1: Fulfillment | P1: Intake At | Q1: Listed At | R1: Sold At | S1: Buyer | T1: Sale Type | U1: Layaway Months | V1: Payment Verified At | W1: Payout Released At
A2: 25053755 | B2: Tom Ford | C2: Oversized Round Sunglasses | D2: Accessory | H2: 8400 | I2: 3000 | J2: 5400 | K2: Carlo Go | L2: Pristine, no visible signs of use | M2: Dust bag, Receipt | N2: tiktok | O2: courier | P2: 45170.485 | Q2: 45181.535 | R2: 45200.622 | S2: Zara Lopez | T2: full_payment | V2: 45201.476 | W2: 45216.498
A3: 75084859 | B3: Hermes | C3: Picotin Lock 18 | D3: Tote | E3: Nata Clemence Leather | F3: Palladium | G3: Stamp B (2023) | H3: 270800 | I3: 32496 | J3: 238304 | K3: Pia Andrada | L3: Excellent, very light wear on corners | M3: Dust bag, Box, Clochette, Lock and Keys | N3: instagram | O3: drop_off | P3: 45161.503 | Q3: 45181.74 | R3: 45201.653 | S3: Marco Cruz | T3: layaway | U3: 2 | V3: 45262.454 | W3: 45274.73
A4: 00096059 | B4: Louis Vuitton | C4: Coussin BB | D4: Handbag | E4: Monogram Beads Noir | H4: 187300 | I4: 18000 | J4: 169300 | K4: Angelica Co | L4: Excellent, very light wear on corners. Microchip present | M4: Dust bag | N4: facebook | O4: walk_in | P4: 45143.562 | Q4: 45161.656 | R4: 45201.759 | S4: Gabrielle Del Rosario | T4: full_payment | V4: 45203.447 | W4: 45210.417
A5: 66584123 | B5: Loewe | C5: Flamenco Tote Bag Large | D5: Tote | E5: Black Nappa Calfskin Leather | H5: 175600 | I5: 18000 | J5: 157600 | K5: Gerald Gatchalian | L5: Excellent, very light wear on corners | M5: Dust bag | N5: instagram | O5: walk_in | P5: 45179.66 | Q5: 45190.625 | R5: 45204.585 | S5: Ramon Torres | T5: full_payment | V5: 45204.627 | W5: 45222.758
A6: 26933051 | B6: Chanel | C6: Le Boy Old Medium | D6: Shoulder Bag | E6: Red Chevron Caviar Leather | F6: Aged Gold | G6: Series 25 | H6: 266600 | I6: 31992 | J6: 234608 | K6: Marco Aguilar | L6: Brand new, never used, complete with tags | M6: Dust bag | N6: instagram | O6: drop_off | P6: 45171.737 | Q6: 45194.486 | R6: 45211.57 | S6: Tina Gatchalian | T6: full_payment | V6: 45212.609 | W6: 45230.664
A7: 15938107 | B7: Louis Vuitton | C7: Capucines Handbag | D7: Handbag | E7: Metallic Gold Goatskin Leather & Mink Fur | H7: 571000 | I7: 68520 | J7: 502480 | K7: Bianca Soriano | L7: Good, visible wear on corners and handles. Microchip present | M7: Dust bag | N7: instagram | O7: drop_off | P7: 45153.722 | Q7: 45162.554 | R7: 45212.806 | S7: Frances Aquino | T7: full_payment | V7: 45212.848 | W7: 45230.551
A8: 33831483 | B8: Chanel | C8: Classic Flap Card Holder | D8: Small Leather Goods | E8: Caramel Quilted Caviar Leather | F8: Light Gold | H8: 52300 | I8: 13000 | J8: 39300 | K8: Bianca Zamora | L8: Pristine, no visible signs of use. Microchip present | M8: Dust bag | N8: instagram | O8: drop_off | P8: 45082.761 | Q8: 45106.585 | R8: 45213.499 | S8: Carla Ramos | T8: full_payment | V8: 45215.791 | W8: 45226.493
A9: 03707963 | B9: Polene | C9: Numéro Neuf East West Ebony Graine Leather | D9: Handbag | H9: 59100 | I9: 13000 | J9: 46100 | K9: Teresa Madrigal | L9: Excellent, very light wear on corners | M9: Dust bag | N9: instagram | O9: drop_off | P9: 45171.66 | Q9: 45194.624 | R9: 45216.49 | S9: Bianca Pascual | T9: full_payment | V9: 45218.459 | W9: 45236.462
A10: 43941435 | B10: Balenciaga | C10: Ville Top Handle Bag | D10: Handbag | E10: Brown Grained Calfskin Leather | F10: Gold | H10: 65900 | I10: 13000 | J10: 52900 | K10: Andrea Uy | L10: Very good, light scratches on hardware | M10: Dust bag, Box | N10: instagram | O10: drop_off | P10: 45177.715 | Q10: 45196.567 | R10: 45220.476 | S10: Michelle Chua | T10: full_payment | V10: 45221.569 | W10: 45231.544
A11: 38471483 | B11: Chanel | C11: 19 Flap Cardholder | D11: Small Leather Goods | E11: Peach Lambskin Leather | F11: Palladium | H11: 50200 | I11: 13000 | J11: 37200 | K11: Rosario Ocampo | L11: Excellent, very light wear on corners. Microchip present | M11: Dust bag, Box, Receipt | N11: walk_in | O11: drop_off | P11: 45169.557 | Q11: 45179.484 | R11: 45220.819 | S11: Gabriel Flores | T11: full_payment | V11: 45222.492 | W11: 45230.72
A12: 63035195 | B12: Bally | C12: Tirk Mens Coffee Travel Long Wallet | D12: Wallet | H12: 25100 | I12: 10000 | J12: 15100 | K12: Yasmin Ilagan | L12: Good, visible wear on corners and handles | M12: Dust bag, Receipt | N12: messenger | O12: drop_off | P12: 45186.455 | Q12: 45200.687 | R12: 45227.662 | S12: Christian Mendoza | T12: full_payment | V12: 45228.78 | W12: 45234.432
A13: 41567547 | B13: Louis Vuitton | C13: Speedy 30 | D13: Handbag | E13: Damier Ebene Canvas | F13: Gold | H13: 76300 | I13: 13000 | J13: 63300 | K13: Carlo Madrigal | L13: Very good, light scratches on hardware. Microchip present | M13: Dust bag, Receipt | N13: walk_in | O13: drop_off | P13: 45177.59 | Q13: 45196.505 | R13: 45230.772 | S13: Eduardo Zamora | T13: full_payment | V13: 45232.439 | W13: 45246.77
A14: 31702587 | B14: Louis Vuitton | C14: Montaigne BB | D14: Handbag | E14: Taupe Monogram Empreinte Leather | G14: SP1197 | H14: 133800 | I14: 18000 | J14: 115800 | K14: Kim De Leon | L14: Very good, light scratches on hardware | M14: Dust bag, Box | N14: messenger | O14: drop_off | P14: 45194.605 | Q14: 45216.621 | R14: 45233.69 | S14: Pauline Lacson | T14: full_payment | V14: 45233.731 | W14: 45250.717
A15: 34498875 | B15: Bottega Veneta | C15: Red Multicolor Karung Flap Long Wallet | D15: Wallet | H15: 18900 | I15: 6000 | J15: 12900 | K15: Carla Santos | L15: Excellent, very light wear on corners | M15: Dust bag | N15: whatsapp | O15: drop_off | P15: 45162.78 | Q15: 45173.733 | R15: 45234.577 | S15: Frances Lacson | T15: full_payment | V15: 45235.542 | W15: 45248.651
A16: 07074875 | B16: Chanel | C16: Boy Small Chevron | D16: Shoulder Bag | E16: Black Caviar Leather | F16: Aged Gold | G16: Series 24 | H16: 289000 | I16: 34680 | J16: 254320 | K16: Adrian Castillo | L16: Pristine, no visible signs of use | M16: Dust bag, Box | N16: messenger | O16: walk_in | P16: 45082.652 | Q16: 45102.721 | R16: 45235.532 | S16: Danica Ramos | T16: full_payment | V16: 45235.717 | W16: 45248.6
A17: 50862139 | B17: Christian Dior | C17: Lady Dior Medium | D17: Handbag | E17: Dark Red Cannage Quilted Lambskin Leather | F17: Light Gold | H17: 266600 | I17: 31992 | J17: 234608 | K17: Marco Aguilar | L17: Good, visible wear on corners and handles | M17: Dust bag | N17: facebook | O17: courier | P17: 45196.488 | Q17: 45213.509 | R17: 45237.775 | S17: Bea Torres | T17: full_payment | V17: 45237.817 | W17: 45248.513
A18: 26186555 | B18: Gucci | C18: Mini Torchon Top Handle Shoulder Bag | D18: Shoulder Bag | E18: Black GG Marmont Matelasse Calfskin Leather | H18: 81600 | I18: 13000 | J18: 68600 | K18: Miguel Santos | L18: Pristine, no visible signs of use | M18: Dust bag | N18: email | O18: courier | P18: 45119.492 | Q18: 45129.719 | R18: 45243.463 | S18: Erika De Leon | T18: full_payment | V18: 45245.778 | W18: 45256.595
A19: 10087227 | B19: Gucci | C19: Horsebit 1955 Soft Small East West Shoulder Bag Supreme Canvas | D19: Shoulder Bag | H19: 128600 | I19: 18000 | J19: 110600 | K19: Kim Santos | L19: Excellent, very light wear on corners | M19: Dust bag, Box | N19: website | O19: pickup | P19: 45188.449 | Q19: 45212.756 | R19: 45243.535 | S19: Maria Velasco | T19: full_payment | V19: 45243.681 | W19: 45252.748
A20: 40964667 | B20: Chanel | C20: Boy Flap Compact Wallet | D20: Wallet | E20: Purple Caviar Leather | F20: Light Gold | G20: Series 29 | H20: 49000 | I20: 10000 | J20: 39000 | K20: Rafael Valdez | L20: Excellent, very light wear on corners | M20: Dust bag, Box, Authenticity card | N20: instagram | O20: walk_in | P20: 45213.606 | Q20: 45229.619 | R20: 45244.688 | S20: Eduardo Ocampo | T20: full_payment | V20: 45244.73 | W20: 45258.482
A21: 34665019 | B21: Hermes | C21: Kelly Wallet | D21: Wallet | E21: Epsom Leather | F21: Palladium | H21: 221800 | I21: 26616 | J21: 195184 | K21: Miguel Santos | L21: Very good, light scratches on hardware | M21: Dust bag, Box, Clochette, Lock and Keys | N21: instagram | O21: courier | P21: 45222.64 | Q21: 45235.676 | R21: 45244.723 | S21: Michelle Navarro | T21: full_payment | V21: 45244.765 | W21: 45258.708
A22: 38685243 | B22: Hermes | C22: Bride-a-Brac Vanity Case | D22: Crossbody | E22: Orange Toile Canvas | F22: Palladium | H22: 59400 | I22: 13000 | J22: 46400 | K22: Katrina Lim | L22: Very good, light scratches on hardware | M22: Dust bag, Box, Receipt, Felt | N22: email | O22: drop_off | P22: 45187.483 | Q22: 45207.619 | R22: 45245.795 | S22: Rica Cojuangco | T22: full_payment | V22: 45246.681 | W22: 45261.433
A23: 42022459 | B23: Chanel | C23: Coco Handle Medium | D23: Handbag | E23: Red Quilted Caviar Leather Aged | F23: Aged Gold | G23: Series 27 | H23: 244200 | I23: 29304 | J23: 214896 | K23: Mika Reyes | L23: Excellent, very light wear on corners | M23: Dust bag, Box, Authenticity card | N23: instagram | O23: walk_in | P23: 45202.762 | Q23: 45214.674 | R23: 45250.635 | S23: Nina Roxas | T23: full_payment | V23: 45252.424 | W23: 45261.61
A24: 65969211 | B24: Saint Laurent | C24: College Bag Medium | D24: Handbag | E24: Burgundy Monogram Chevron Sheepskin Leather | F24: Ruthenium | H24: 83400 | I24: 13000 | J24: 70400 | K24: Hannah Roxas | L24: Good, visible wear on corners and handles | M24: Dust bag, Box | N24: facebook | O24: drop_off | P24: 45219.754 | Q24: 45228.513 | R24: 45252.758 | S24: Nicole Laurel | T24: full_payment | V24: 45254.658 | W24: 45264.544
A25: 77972283 | B25: Hermes | C25: Picotin Lock 22 | D25: Tote | E25: Rouge Casaque Clemence Leather | F25: Palladium | G25: Stamp X (2016) | H25: 187300 | I25: 18000 | J25: 169300 | K25: Jasmine Laurel | L25: Good, visible wear on corners and handles | M25: Dust bag, Box, Rain cover | N25: instagram | O25: pickup | P25: 45198.474 | Q25: 45211.719 | R25: 45256.725 | S25: Benjamin Madrigal | T25: full_payment | V25: 45257.683 | W25: 45275.581
A26: 28883003 | B26: Gucci | C26: Guccissima Black Signature Calfskin Leather Bifold Wallet | D26: Wallet | H26: 42800 | I26: 10000 | J26: 32800 | K26: Miguel Santos | L26: Pristine, no visible signs of use | M26: Dust bag, Box | N26: walk_in | O26: walk_in | P26: 45199.486 | Q26: 45215.658 | R26: 45257.722 | S26: Vincent Del Rosario | T26: full_payment | V26: 45259.605 | W26: 45273.636
A27: 07974459 | B27: Gucci | C27: Dionysus Mini GG Supreme Coated Canvas | D27: Shoulder Bag | H27: 65900 | I27: 13000 | J27: 52900 | K27: Paolo Laurel | L27: Brand new, never used, complete with tags | M27: Dust bag, Box | N27: walk_in | O27: walk_in | P27: 45239.644 | Q27: 45251.458 | R27: 45260.459 | S27: Danica Roxas | T27: full_payment | V27: 45262.533 | W27: 45271.533
A28: 16644411 | B28: Chanel | C28: Mini Coco Handle | D28: Handbag | E28: Black Quilted Caviar Leather | F28: Light Gold | H28: 317000 | I28: 38040 | J28: 278960 | K28: Hannah Yap | L28: Brand new, never used, complete with tags. Microchip present | M28: Dust bag, Box, Authenticity card | N28: instagram | O28: courier | P28: 45212.482 | Q28: 45227.456 | R28: 45260.542 | S28: Olivia Soriano | T28: full_payment | V28: 45261.68 | W28: 45270.714
A29: 56374075 | B29: Chanel | C29: Wallet On Chain | D29: Crossbody | E29: Iridescent Lambskin Leather | H29: 175600 | I29: 18000 | J29: 157600 | K29: Paolo Laurel | L29: Excellent, very light wear on corners. Microchip present | M29: Dust bag, Box | N29: instagram | O29: courier | P29: 45185.535 | Q29: 45203.565 | R29: 45261.49 | S29: Carla Rivera | T29: full_payment | V29: 45261.562 | W29: 45272.733
A30: 68136251 | B30: Chanel | C30: Flap Card Holder | D30: Small Leather Goods | E30: Gray Lambskin Leather | F30: Light Gold | G30: Series 31 | H30: 50200 | I30: 13000 | J30: 37200 | K30: Zara Domingo | L30: Pristine, no visible signs of use | M30: Dust bag, Receipt | N30: instagram | O30: courier | P30: 45216.662 | Q30: 45229.774 | R30: 45261.66 | S30: Jericho Castro | T30: full_payment | V30: 45263.753 | W30: 45270.42
A31: 12096315 | B31: Givenchy | C31: White Rubber Pool Slides | D31: Shoes | H31: 24000 | I31: 10000 | J31: 14000 | K31: Antonio Aquino | L31: Good, visible wear on corners and handles. Size 42 EU | M31: Dust bag, Box | N31: website | O31: walk_in | P31: 45203.524 | Q31: 45227.757 | R31: 45261.817 | S31: Patricia Javier | T31: full_payment | V31: 45262.446 | W31: 45269.519
A32: 90086203 | B32: Louis Vuitton | C32: Neo Noe BB | D32: Handbag | E32: Navy Blue Epi Leather | F32: Silver | H32: 86800 | I32: 13000 | J32: 73800 | K32: Miguel Santos | L32: Excellent, very light wear on corners. Microchip present | M32: Dust bag, Box | N32: messenger | O32: walk_in | P32: 45215.72 | Q32: 45235.613 | R32: 45262.616 | S32: Mika Sy | T32: full_payment | V32: 45264.771 | W32: 45273.765
A33: 92724283 | B33: Chanel | C33: Paris Limited Edition Double Flap Bag Medium | D33: Shoulder Bag | E33: Black Lambskin Leather | F33: Mix | G33: Series 3 | H33: 210600 | I33: 25272 | J33: 185328 | K33: Miguel Santos | L33: Pristine, no visible signs of use | M33: Dust bag, Box | N33: website | O33: walk_in | P33: 45111.552 | Q33: 45131.646 | R33: 45262.669 | S33: Teresa Ayala | T33: full_payment | V33: 45264.575 | W33: 45271.678
A34: 27633979 | B34: Louis Vuitton | C34: Neo Noe MM Bi-Color Monogram Empreinte Leather | D34: Handbag | H34: 112900 | I34: 18000 | J34: 94900 | K34: Ramon Javier | L34: Excellent, very light wear on corners. Microchip present | M34: Dust bag, Box | N34: instagram | O34: drop_off | P34: 45188.446 | Q34: 45212.492 | R34: 45266.46 | S34: Veronica Aguilar | T34: full_payment | V34: 45266.66 | W34: 45274.43
A35: 61516091 | B35: Loewe | C35: Mini Gate Ash Blue | D35: Crossbody | E35: Smooth Calfskin Leather Crossbody Bag | H35: 86800 | I35: 13000 | J35: 73800 | K35: Kim Tuason | L35: Excellent, very light wear on corners | M35: Dust bag, Box | N35: instagram | O35: drop_off | P35: 45234.417 | Q35: 45252.577 | R35: 45266.692 | S35: Patricia Tuason | T35: full_payment | V35: 45268.56 | W35: 45275.479
A36: 33980731 | B36: Louis Vuitton | C36: OntheGo MM | D36: Tote | E36: Black Monogram Empreinte Leather | F36: Gold | H36: 107700 | I36: 18000 | J36: 89700 | K36: Ana Gonzales | L36: Very good, light scratches on hardware. Microchip present | M36: Dust bag, Box | N36: whatsapp | O36: drop_off | P36: 45232.469 | Q36: 45248.634 | R36: 45266.812 | S36: Jasmine Castillo | T36: full_payment | V36: 45268.531 | W36: 45275.484
A37: 82160955 | B37: Bottega Veneta | C37: Mount Envelope Small Green | D37: Handbag | E37: Grained Calfskin Leather Bag | H37: 112900 | I37: 18000 | J37: 94900 | K37: Vincent Andrada | L37: Pristine, no visible signs of use | M37: Dust bag, Receipt | N37: walk_in | O37: drop_off | P37: 45199.781 | Q37: 45218.52 | R37: 45267.467 | S37: Rafael Uy | T37: full_payment | V37: 45268.74 | W37: 45281.528
A38: 81669435 | B38: Hermes | C38: Pencilver Charm with Notebook | D38: Accessory | H38: 86800 | I38: 13000 | J38: 73800 | K38: Mika Soriano | L38: Very good, light scratches on hardware | M38: Dust bag, Box, Felt | N38: tiktok | O38: courier | P38: 45250.701 | Q38: 45263.755 | R38: 45267.503 | S38: Hannah Laurel | T38: full_payment | V38: 45268.521 | W38: 45284.686
A39: 15685691 | B39: Gucci | C39: GG Bi-Fold Wallet | D39: Wallet | E39: Beige & Ebony Supreme Monogram Canvas | H39: 37600 | I39: 10000 | J39: 27600 | K39: Lara Aquino | L39: Very good, light scratches on hardware | M39: Dust bag, Box, Receipt | N39: instagram | O39: pickup | P39: 45151.434 | Q39: 45164.768 | R39: 45267.785 | S39: Regina Ocampo | T39: full_payment | V39: 45269.756 | W39: 45275.483
A40: 12261435 | B40: Louis Vuitton | C40: Ostrich Leather Zippy Card Holder | D40: Wallet | H40: 22000 | I40: 10000 | J40: 12000 | K40: Ramon Tan | L40: Excellent, very light wear on corners | M40: Dust bag, Box, Receipt | N40: walk_in | O40: courier | P40: 45219.576 | Q40: 45233.48 | R40: 45270.537 | S40: Antonio Sy | T40: full_payment | V40: 45271.427 | W40: 45289.769
A41: 12737339 | B41: Christian Dior | C41: Book Tote Bag Medium | D41: Tote | E41: White & Gray | H41: 145800 | I41: 18000 | J41: 127800 | K41: Pauline Valdez | L41: Very good, light scratches on hardware | M41: Dust bag, Box | N41: facebook | O41: courier | P41: 45240.452 | Q41: 45250.534 | R41: 45271.517 | S41: Veronica Navarro | T41: full_payment | V41: 45273.686 | W41: 45288.556
A42: 82389307 | B42: Louis Vuitton | C42: Neo Noe Bucket Bag MM | D42: Handbag | E42: Limited Edition Jungle Monogram Giant Canvas | G42: SP3169 | H42: 97200 | I42: 13000 | J42: 84200 | K42: Carlo Lim | L42: Excellent, very light wear on corners | M42: Dust bag | N42: walk_in | O42: drop_off | P42: 45236.575 | Q42: 45247.424 | R42: 45274.624 | S42: Maria Ocampo | T42: full_payment | V42: 45276.728 | W42: 45285.755
A43: 92647227 | B43: Christian Dior | C43: Caro Large | D43: Handbag | E43: Dark Beige Calfskin Cannage Leather | H43: 181500 | I43: 18000 | J43: 163500 | K43: Katrina Javier | L43: Excellent, very light wear on corners | M43: Dust bag, Box | N43: instagram | O43: walk_in | P43: 45239.417 | Q43: 45258.567 | R43: 45275.748 | S43: Denise Zamora | T43: layaway | U43: 2 | V43: 45336.581 | W43: 45342.633
A44: 55142459 | B44: Chanel | C44: Grand Shopping Tote | D44: Tote | E44: Beige Clair Quilted Caviar Leather | G44: Series 16 | H44: 154700 | I44: 18000 | J44: 136700 | K44: Isabel Gatchalian | L44: Pristine, no visible signs of use | M44: Dust bag, Box, Receipt | N44: instagram | O44: courier | P44: 45189.705 | Q44: 45210.71 | R44: 45277.572 | S44: Maria Gatchalian | T44: full_payment | V44: 45278.585 | W44: 45292.784
A45: 63452987 | B45: Gucci | C45: Messenger Bag | D45: Crossbody | E45: GG Guccissima Web Black Canvas | H45: 54200 | I45: 13000 | J45: 41200 | K45: Kim Santos | L45: Very good, light scratches on hardware | M45: Dust bag, Box | N45: walk_in | O45: drop_off | P45: 45219.659 | Q45: 45236.674 | R45: 45277.655 | S45: Gabriel Pascual | T45: full_payment | V45: 45279.601 | W45: 45287.59
A46: 78893627 | B46: Bottega Veneta | C46: Stretch Mule Sandals Black | D46: Shoes | E46: Lambskin Leather | H46: 27200 | I46: 10000 | J46: 17200 | K46: Tina Ilagan | L46: Pristine, no visible signs of use. Size 39 EU | M46: Dust bag, Box | N46: facebook | O46: courier | P46: 45229.429 | Q46: 45253.684 | R46: 45277.707 | S46: Lourdes Bautista | T46: full_payment | V46: 45279.747 | W46: 45289.634
A47: 00549179 | B47: Hermes | C47: Kelly To Go | D47: Crossbody | E47: Gold Epsom Leather | F47: Gold | G47: Stamp B (2023) | H47: 378600 | I47: 45432 | J47: 333168 | K47: Angelica Co | L47: Pristine, no visible signs of use | M47: Dust bag, Receipt, Clochette, Lock and Keys | N47: walk_in | O47: pickup | P47: 45243.637 | Q47: 45258.518 | R47: 45279.821 | S47: Benjamin Uy | T47: full_payment | V47: 45279.863 | W47: 45287.717
A48: 38368827 | B48: Chanel | C48: Color Burst Clutch | D48: Clutch | E48: Lambskin Leather With Black Polished Metal Chain Strap Bag | H48: 175600 | I48: 18000 | J48: 157600 | K48: Lara Aquino | L48: Good, visible wear on corners and handles. Microchip present | M48: Dust bag, Box, Receipt | N48: whatsapp | O48: pickup | P48: 45146.483 | Q48: 45167.585 | R48: 45280.79 | S48: Ramon Soriano | T48: full_payment | V48: 45280.831 | W48: 45287.469
A49: 86818363 | B49: Hugo Boss | C49: Slim Fit Polo Shirt for Men Black | D49: Clothing | H49: 13000 | I49: 6000 | J49: 7000 | K49: Pauline Ong | L49: Excellent, very light wear on corners. Size XL | M49: Tags | N49: messenger | O49: courier | P49: 45215.527 | Q49: 45234.574 | R49: 45281.595 | S49: Trisha Roxas | T49: full_payment | V49: 45283.445 | W49: 45294.581
A50: 10484283 | B50: Chanel | C50: Classic Double Flap Small | D50: Shoulder Bag | E50: Black Caviar Leather | F50: Gold | G50: Series 27 | H50: 518600 | I50: 62232 | J50: 456368 | K50: Gerald Gatchalian | L50: Very good, light scratches on hardware | M50: Dust bag, Box | N50: whatsapp | O50: courier | P50: 45260.678 | Q50: 45276.679 | R50: 45282.672 | S50: Gabrielle Tan | T50: full_payment | V50: 45283.435 | W50: 45296.767
A51: 06516027 | B51: Chanel | C51: Grand Shopping Tote Bag | D51: Tote | E51: Black Quilted Caviar Leather | F51: Gold | G51: Series 15 | H51: 195500 | I51: 18000 | J51: 177500 | K51: Nina Yap | L51: Brand new, never used, complete with tags | M51: Dust bag, Box, Receipt, Authenticity card | N51: messenger | O51: pickup | P51: 45260.534 | Q51: 45272.593 | R51: 45283.489 | S51: Margarita Salazar | T51: full_payment | V51: 45285.511 | W51: 45298.493
A52: 25184315 | B52: Louis Vuitton | C52: Buci Crossbody Bag | D52: Crossbody | E52: Off-White Beige Epi Leather | F52: Silver | H52: 92000 | I52: 13000 | J52: 79000 | K52: Hannah Roxas | L52: Very good, light scratches on hardware. Microchip present | M52: Dust bag, Box | N52: instagram | O52: courier | P52: 45251.711 | Q52: 45264.467 | R52: 45283.59 | S52: Erika Domingo | T52: full_payment | V52: 45284.698 | W52: 45295.494
A53: 35882811 | B53: Christian Dior | C53: Essential Tote Bag | D53: Tote | E53: Black Calfskin Leather | F53: Light Gold | H53: 156600 | I53: 18000 | J53: 138600 | K53: Nicole Go | L53: Very good, light scratches on hardware | M53: Dust bag, Box, Receipt | N53: website | O53: courier | P53: 45261.492 | Q53: 45275.522 | R53: 45285.553 | S53: Miguel Roxas | T53: layaway | U53: 2 | V53: 45345.584 | W53: 45358.716
A54: 26474299 | B54: Gucci | C54: Blondie Shoulder Bag Small | D54: Shoulder Bag | E54: GG Supreme Canvas | F54: Gold | H54: 86800 | I54: 13000 | J54: 73800 | K54: Miguel Javier | L54: Very good, light scratches on hardware | M54: Dust bag, Box | N54: walk_in | O54: walk_in | P54: 45255.715 | Q54: 45271.579 | R54: 45285.745 | S54: Jessa Cojuangco | T54: full_payment | V54: 45285.787 | W54: 45293.753
A55: 82261563 | B55: Louis Vuitton | C55: Twist Lock MM | D55: Handbag | E55: Damier Graphite Calf Leather | H55: 102500 | I55: 18000 | J55: 84500 | K55: Teresa Pascual | L55: Excellent, very light wear on corners. Microchip present | M55: Dust bag, Box, Receipt | N55: website | O55: courier | P55: 45238.436 | Q55: 45255.728 | R55: 45288.466 | S55: Bea Dela Cruz | T55: full_payment | V55: 45289.453 | W55: 45299.51
A56: 02295611 | B56: Chanel | C56: Boy Old Medium | D56: Shoulder Bag | E56: Striking Red Micro Quilted Calfskin Leather | F56: Light Gold | G56: Series 24 | H56: 244200 | I56: 29304 | J56: 214896 | K56: Adrian Manalo | L56: Brand new, never used, complete with tags | M56: Dust bag, Box, Receipt, Authenticity card | N56: facebook | O56: courier | P56: 45261.738 | Q56: 45282.691 | R56: 45290.704 | S56: Yasmin Reyes | T56: full_payment | V56: 45290.746 | W56: 45299.447
A57: 04216891 | B57: Gucci | C57: Ophidia Top Handle Bag Medium GG Supreme Canvas | D57: Handbag | H57: 165200 | I57: 18000 | J57: 147200 | K57: Benjamin Gonzales | L57: Very good, light scratches on hardware | M57: Dust bag, Box, Receipt | N57: instagram | O57: drop_off | P57: 45198.621 | Q57: 45222.496 | R57: 45292.539 | S57: Regina Domingo | T57: full_payment | V57: 45293.474 | W57: 45309.555
A58: 01269051 | B58: Coach | C58: Logo Dark Blue Cotton and Brown Logo Print T-Shirt | D58: Clothing | H58: 13500 | I58: 6000 | J58: 7500 | K58: Bianca Domingo | L58: Brand new, never used, complete with tags. Size L | M58: Tags | N58: instagram | O58: walk_in | P58: 45250.773 | Q58: 45273.68 | R58: 45295.531 | S58: Pia Ocampo | T58: full_payment | V58: 45297.468 | W58: 45303.51
A59: 01339963 | B59: Louis Vuitton | C59: Alma Trunk BB | D59: Handbag | E59: Tan Smooth Calfskin Leather | F59: Gold | H59: 144300 | I59: 18000 | J59: 126300 | K59: Lara Aquino | L59: Good, visible wear on corners and handles. Microchip present | M59: Dust bag | N59: walk_in | O59: pickup | P59: 45257.481 | Q59: 45272.639 | R59: 45295.55 | S59: Daniel Bautista | T59: full_payment | V59: 45296.756 | W59: 45309.651
A60: 87113275 | B60: Hugo Boss | C60: Jersey Polo Shirt | D60: Clothing | E60: Light Beige for Men | H60: 13000 | I60: 6000 | J60: 7000 | K60: Nicole Lopez | L60: Excellent, very light wear on corners. Size L | N60: instagram | O60: drop_off | P60: 45249.443 | Q60: 45265.484 | R60: 45296.705 | S60: Jose Lopez | T60: full_payment | V60: 45298.542 | W60: 45308.474
A61: 96333371 | B61: Chanel | C61: 19 Flap Bag Medium | D61: Shoulder Bag | E61: Black Lambskin Leather | F61: Mix | H61: 333800 | I61: 40056 | J61: 293744 | K61: Paolo Gonzales | L61: Excellent, very light wear on corners. Microchip present | M61: Dust bag | N61: walk_in | O61: drop_off | P61: 45245.665 | Q61: 45262.613 | R61: 45303.581 | S61: Celeste Castillo | T61: full_payment | V61: 45303.741 | W61: 45317.603
A62: 93085499 | B62: Chanel | C62: Trendy CC Wallet On Chain | D62: Crossbody | E62: Black Chevron Lambskin Leather | F62: Light Gold | G62: Series 25 | H62: 179100 | I62: 18000 | J62: 161100 | K62: Camille Go | L62: Excellent, very light wear on corners | M62: Dust bag, Authenticity card | N62: walk_in | O62: drop_off | P62: 45254.55 | Q62: 45268.728 | R62: 45305.555 | S62: Trisha Sy | T62: full_payment | V62: 45306.523 | W62: 45319.688
A63: 96427579 | B63: Chanel | C63: Le Boy New Medium | D63: Shoulder Bag | E63: Pink Chevron Lambskin Leather | F63: Silver | G63: Series 22 | H63: 255400 | I63: 30648 | J63: 224752 | K63: Jose Cojuangco | L63: Very good, light scratches on hardware | M63: Dust bag, Box, Receipt, Authenticity card | N63: instagram | O63: pickup | P63: 45275.516 | Q63: 45286.565 | R63: 45307.656 | S63: Mika Navarro | T63: full_payment | V63: 45307.734 | W63: 45313.641
A64: 74109755 | B64: Gucci | C64: GG Marmont Small Shoulder Bag | D64: Shoulder Bag | E64: Porcelain Rose Chevron Quilted Matelasse Calfskin Leather | F64: Gold | H64: 93900 | I64: 13000 | J64: 80900 | K64: Michelle Aquino | L64: Very good, light scratches on hardware | M64: Dust bag, Box | N64: walk_in | O64: drop_off | P64: 45228.425 | Q64: 45250.784 | R64: 45307.695 | S64: Vincent Ilagan | T64: full_payment | V64: 45309.57 | W64: 45324.669
A65: 99313723 | B65: Gucci | C65: Bauletto Duffle Top Handle Bag Mini | D65: Handbag | E65: Mystic White Koi Calfskin Web Leather | H65: 96200 | I65: 13000 | J65: 83200 | K65: Jessa Panlilio | L65: Excellent, very light wear on corners | M65: Dust bag, Box, Receipt | N65: walk_in | O65: drop_off | P65: 45288.503 | Q65: 45297.428 | R65: 45308.663 | S65: Margarita Garcia | T65: full_payment | V65: 45310.678 | W65: 45324.612
A66: 46148411 | B66: Gucci | C66: GG Marmont Super Mini Bag | D66: Handbag | E66: Beige Matellase Leather | F66: Ruthenium | H66: 71100 | I66: 13000 | J66: 58100 | K66: Marco Del Rosario | L66: Pristine, no visible signs of use | M66: Dust bag, Box | N66: whatsapp | O66: courier | P66: 45275.714 | Q66: 45289.498 | R66: 45309.787 | S66: Rica De Leon | T66: full_payment | V66: 45310.755 | W66: 45324.495
A67: 12681647 | B67: Chanel | C67: Classic Double Flap Medium | D67: Shoulder Bag | E67: Mint Green Quilted Caviar Leather | F67: Light Gold | H67: 537400 | I67: 64488 | J67: 472912 | K67: Yasmin Garcia | L67: Very good, light scratches on hardware. Microchip present | M67: Dust bag, Receipt | N67: walk_in | O67: walk_in | P67: 45270.44 | Q67: 45284.51 | R67: 45310.487 | S67: Hannah Garcia | T67: full_payment | V67: 45312.53 | W67: 45329.614
A68: 13874107 | B68: Hermes | C68: Silk'In Compact Wallet | D68: Wallet | E68: Burgundy Epsom Leather | F68: Palladium | G68: Stamp A (2017) | H68: 57500 | I68: 13000 | J68: 44500 | K68: Andrea Laurel | L68: Excellent, very light wear on corners | M68: Dust bag, Rain cover | N68: messenger | O68: drop_off | P68: 45275.653 | Q68: 45284.503 | R68: 45313.669 | S68: Jose Ramos | T68: full_payment | V68: 45314.64 | W68: 45322.556
A69: 87637563 | B69: Hugo Boss | C69: Jersey Polo Shirt | D69: Clothing | E69: Navy/Dark Blue for Men | H69: 13000 | I69: 6000 | J69: 7000 | K69: Yasmin Garcia | L69: Pristine, no visible signs of use. Size L | M69: Tags, Dust bag | N69: walk_in | O69: drop_off | P69: 45250.678 | Q69: 45273.503 | R69: 45313.787 | S69: Erika Tuason | T69: full_payment | V69: 45314.699 | W69: 45331.667
A70: 64305211 | B70: Chanel | C70: CC Filigree Wallet on Chain | D70: Crossbody | E70: Beige | F70: Gold | G70: Series 30 | H70: 199000 | I70: 18000 | J70: 181000 | K70: Marco Aguilar | L70: Excellent, very light wear on corners | M70: Dust bag | N70: messenger | O70: walk_in | P70: 45219.562 | Q70: 45229.738 | R70: 45315.725 | S70: Kim Torres | T70: full_payment | V70: 45315.767 | W70: 45322.782
A71: 15291963 | B71: Prada | C71: Saffiano Leather | D71: Handbag | E71: Black Phone Carrier | H71: 81600 | I71: 13000 | J71: 68600 | K71: Rica Mercado | L71: Brand new, never used, complete with tags | M71: Dust bag, Box | N71: whatsapp | O71: drop_off | P71: 45280.791 | Q71: 45289.742 | R71: 45316.535 | S71: Bea Ilagan | T71: full_payment | V71: 45318.627 | W71: 45327.512
A72: 853650511 | B72: Chanel | C72: CC Espadrilles | D72: Shoes | E72: Beige Lambskin Leather and Black Toe | H72: 52300 | I72: 13000 | J72: 39300 | K72: Ramon Sy | L72: Excellent, very light wear on corners. Size 37 EU | M72: Dust bag, Box | N72: instagram | O72: walk_in | P72: 45278.528 | Q72: 45302.714 | R72: 45317.546 | S72: Rafael Torres | T72: full_payment | V72: 45319.453 | W72: 45326.759
A73: 80977211 | B73: Louis Vuitton | C73: Metis | D73: Handbag | E73: Rose Poudre Empreinte Monogram Canvas | G73: DU1177 | H73: 117600 | I73: 18000 | J73: 99600 | K73: Miguel Javier | L73: Brand new, never used, complete with tags | M73: Dust bag, Box | N73: email | O73: drop_off | P73: 45269.733 | Q73: 45278.49 | R73: 45317.697 | S73: Christian Cruz | T73: full_payment | V73: 45319.524 | W73: 45334.567
A74: 38668091 | B74: Chanel | C74: 19 Wallet on Chain | D74: Crossbody | E74: Light Green Lambskin Leather | F74: Gold | H74: 204900 | I74: 24588 | J74: 180312 | K74: Christian Aquino | L74: Very good, light scratches on hardware. Microchip present | M74: Dust bag, Box, Receipt | N74: messenger | O74: drop_off | P74: 45244.65 | Q74: 45263.647 | R74: 45322.604 | S74: Ana Escudero | T74: layaway | U74: 1 | V74: 45356.487 | W74: 45369.44
A75: 02413371 | B75: Saint Laurent | C75: Perforated Star | D75: Crossbody | E75: Black Calfskin Leather Crossbody Bag | H75: 65900 | I75: 13000 | J75: 52900 | K75: Lara Torres | L75: Pristine, no visible signs of use | M75: Dust bag, Box | N75: whatsapp | O75: courier | P75: 45275.791 | Q75: 45293.597 | R75: 45323.765 | S75: Eduardo Panlilio | T75: full_payment | V75: 45324.729 | W75: 45335.525
A76: 16831803 | B76: Chloe | C76: Penelope Medium | D76: Handbag | E76: Blue-Grey Calfskin Leather Cross Body Bag | H76: 65900 | I76: 13000 | J76: 52900 | K76: Lara Aquino | L76: Very good, light scratches on hardware | M76: Dust bag, Receipt | N76: facebook | O76: courier | P76: 45165.705 | Q76: 45174.591 | R76: 45324.622 | S76: Erika Co | T76: full_payment | V76: 45326.422 | W76: 45339.574
A77: 13697339 | B77: Louis Vuitton | C77: Keepall Bandouliere Flight Mode Collection | D77: Handbag | E77: Monogram Canvas Cowhide Leather | F77: Gold | H77: 175600 | I77: 18000 | J77: 157600 | K77: Kim Lacson | L77: Brand new, never used, complete with tags. Microchip present | M77: Dust bag, Box | N77: messenger | O77: courier | P77: 45290.776 | Q77: 45303.676 | R77: 45326.613 | S77: Lourdes Lopez | T77: layaway | U77: 3 | V77: 45421.565 | W77: 45431.632
A78: 47779643 | B78: Chanel | C78: Classic Double Flap Medium | D78: Shoulder Bag | E78: Black Caviar Leather | F78: Gold | G78: Series 28 | H78: 485000 | I78: 58200 | J78: 426800 | K78: Angelica Andrada | L78: Good, visible wear on corners and handles | M78: Dust bag, Box, Receipt, Authenticity card | N78: walk_in | O78: pickup | P78: 45303.578 | Q78: 45317.709 | R78: 45328.479 | S78: Zara Tuason | T78: full_payment | V78: 45330.714 | W78: 45344.477
A79: 88363835 | B79: Miu Miu | C79: Ballerina Flats | D79: Shoes | E79: Neutral Beige | H79: 43800 | I79: 10000 | J79: 33800 | K79: Michelle Aquino | L79: Excellent, very light wear on corners. Size 37 | M79: Dust bag, Box, Receipt | N79: instagram | O79: pickup | P79: 45286.417 | Q79: 45305.63 | R79: 45329.71 | S79: Nina Lopez | T79: full_payment | V79: 45331.783 | W79: 45342.651
A80: 73697083 | B80: Hermes | C80: Geta | D80: Handbag | E80: Caramel Chyvre Mysore Leather | F80: Palladium | G80: Stamp U (2022) | H80: 367400 | I80: 44088 | J80: 323312 | K80: Danica Castillo | L80: Very good, light scratches on hardware | M80: Dust bag, Box, Clochette, Lock and Keys | N80: whatsapp | O80: drop_off | P80: 45302.528 | Q80: 45317.556 | R80: 45331.55 | S80: Vincent Villanueva | T80: full_payment | V80: 45332.626 | W80: 45340.753
A81: 31861051 | B81: Hermes | C81: Paris Loafers Chevre Beige | D81: Shoes | H81: 69000 | I81: 13000 | J81: 56000 | K81: Miguel Santos | L81: Very good, light scratches on hardware. Size 39.5 EU | M81: Dust bag, Box, Clochette, Lock and Keys | N81: walk_in | O81: drop_off | P81: 45320.658 | Q81: 45329.622 | R81: 45335.799 | S81: Trisha Valdez | T81: full_payment | V81: 45337.461 | W81: 45345.673
A82: 94073147 | B82: Hermes | C82: Kelly Strap | D82: Handbag | E82: Chai Swift Leather | F82: Gold | G82: Stamp W (2024) | H82: 112900 | I82: 18000 | J82: 94900 | K82: Paolo Chua | L82: Very good, light scratches on hardware | M82: Dust bag, Box, Receipt, Felt | N82: facebook | O82: pickup | P82: 45302.458 | Q82: 45317.492 | R82: 45337.544 | S82: Carmela Tan | T82: full_payment | V82: 45337.745 | W82: 45354.523
A83: 42250299 | B83: Balenciaga | C83: Neo Cagole City Bag | D83: Shoulder Bag | E83: Hot Pink Arena Lambskin Leather | H83: 85200 | I83: 13000 | J83: 72200 | K83: Jasmine Laurel | L83: Brand new, never used, complete with tags | M83: Dust bag, Box | N83: website | O83: drop_off | P83: 45305.642 | Q83: 45325.456 | R83: 45339.753 | S83: Teresa Ong | T83: full_payment | V83: 45340.671 | W83: 45358.713
A84: 13451835 | B84: Louis Vuitton | C84: Capucines Mini Handbag | D84: Handbag | E84: Peach Taurillon Leather | F84: Iridescent Rainbow | H84: 244200 | I84: 29304 | J84: 214896 | K84: Lara Aquino | L84: Good, visible wear on corners and handles. Microchip present | M84: Dust bag, Receipt | N84: messenger | O84: walk_in | P84: 45248.774 | Q84: 45272.765 | R84: 45344.795 | S84: Enrique Gatchalian | T84: full_payment | V84: 45344.837 | W84: 45359.706
A85: 61624379 | B85: Christian Dior | C85: Mini Caro Coin Purse | D85: Small Leather Goods | E85: Black Cannage Quilted Leather | F85: Gold | H85: 19900 | I85: 6000 | J85: 13900 | K85: Adrian Tomas | L85: Very good, light scratches on hardware | M85: Dust bag, Box | N85: walk_in | O85: walk_in | P85: 45275.488 | Q85: 45289.738 | R85: 45345.701 | S85: Yasmin Del Rosario | T85: full_payment | V85: 45345.742 | W85: 45357.684
A86: 16095291 | B86: Loewe | C86: Puzzle Edge Bag Small | D86: Handbag | E86: Angora Multi Tone Beige Calfskin Leather | F86: Gold | H86: 144300 | I86: 18000 | J86: 126300 | K86: Camille Lopez | L86: Very good, light scratches on hardware | M86: Dust bag | N86: instagram | O86: courier | P86: 45312.761 | Q86: 45331.679 | R86: 45346.644 | S86: Vincent Ilagan | T86: full_payment | V86: 45347.553 | W86: 45360.788
A87: 55867451 | B87: Hermes | C87: Chain Frandole Bracelet Sterling Silver 18cm | D87: Jewelry | H87: 78300 | I87: 13000 | J87: 65300 | K87: Adrian Castillo | L87: Pristine, no visible signs of use | M87: Dust bag, Receipt | N87: facebook | O87: drop_off | P87: 45307.601 | Q87: 45325.449 | R87: 45348.46 | S87: Iris Tan | T87: full_payment | V87: 45350.713 | W87: 45366.597
A88: 20226619 | B88: Louis Vuitton | C88: Neo Purse | D88: Handbag | E88: Monogram Canvas Bucket Bag | H88: 104300 | I88: 18000 | J88: 86300 | K88: Kim Panlilio | L88: Pristine, no visible signs of use. Microchip present | M88: Dust bag, Box | N88: tiktok | O88: walk_in | P88: 45260.706 | Q88: 45278.752 | R88: 45352.506 | S88: Gabriel Go | T88: full_payment | V88: 45352.533 | W88: 45358.49
A89: 2-73797947 | B89: Chanel | C89: 19 Small | D89: Handbag | E89: Black Quilted Shiny Lambskin | F89: Mix | H89: 333800 | I89: 40056 | J89: 293744 | K89: Iñigo Concepcion | L89: Excellent, very light wear on corners. Microchip present | M89: Dust bag, Receipt | N89: walk_in | O89: walk_in | P89: 45276.569 | Q89: 45293.601 | R89: 45354.704 | S89: Veronica De Leon | T89: full_payment | V89: 45354.789 | W89: 45362.657
A90: 53214267 | B90: Givenchy | C90: Antigona Pouch | D90: Small Leather Goods | E90: Metallic Silver Calf Leather | F90: Silver | H90: 18900 | I90: 6000 | J90: 12900 | K90: Miguel Santos | L90: Excellent, very light wear on corners | M90: Dust bag, Receipt | N90: whatsapp | O90: walk_in | P90: 45333.681 | Q90: 45344.447 | R90: 45355.686 | S90: Kristine Lopez | T90: full_payment | V90: 45356.76 | W90: 45363.488
A91: 74137147 | B91: Chanel | C91: Boy Wallet On Chain | D91: Crossbody | E91: Black Caviar Leather | F91: Aged Gold | G91: Series 26 | H91: 189400 | I91: 18000 | J91: 171400 | K91: Jericho Castro | L91: Excellent, very light wear on corners | M91: Dust bag, Box, Receipt, Authenticity card | N91: walk_in | O91: walk_in | P91: 45243.498 | Q91: 45266.441 | R91: 45356.743 | S91: Adrian Aquino | T91: full_payment | V91: 45357.588 | W91: 45366.728
A92: 99136315 | B92: Hermes | C92: Azap Zip Around Long Wallet | D92: Wallet | E92: Rouge Epsom Leather | F92: Palladium | G92: Stamp X (2016) | H92: 27200 | I92: 10000 | J92: 17200 | K92: Frances Del Rosario | L92: Excellent, very light wear on corners | M92: Dust bag, Box, Receipt, Clochette, Lock and Keys | N92: instagram | O92: drop_off | P92: 45212.431 | Q92: 45230.686 | R92: 45359.501 | S92: Jessa Cruz | T92: full_payment | V92: 45360.738 | W92: 45366.751
A93: 75289403 | B93: Chanel | C93: Classic Double Flap Medium Black Caviar Leather | D93: Shoulder Bag | E93: Gold Hardware | F93: Gold | G93: Series 19 | H93: 507400 | I93: 60888 | J93: 446512 | K93: Katrina Reyes | L93: Brand new, never used, complete with tags | M93: Dust bag, Box, Receipt | N93: instagram | O93: drop_off | P93: 45337.76 | Q93: 45351.502 | R93: 45360.546 | S93: Carlo Uy | T93: layaway | U93: 3 | V93: 45453.471 | W93: 45470.602
A94: 38013755 | B94: Prada | C94: 1MH132 Saffiano Leather Flap Long Wallet | D94: Wallet | E94: Gray | H94: 33000 | I94: 10000 | J94: 23000 | K94: Ramon Tan | L94: Excellent, very light wear on corners | M94: Dust bag | N94: instagram | O94: courier | P94: 45303.61 | Q94: 45315.423 | R94: 45362.622 | S94: Benjamin Chua | T94: full_payment | V94: 45362.623 | W94: 45376.762
A95: 47875899 | B95: Hermes | C95: Giulia Sandals | D95: Shoes | E95: Taupe Calfskin Leather | F95: Palladium | H95: 47100 | I95: 10000 | J95: 37100 | K95: Teresa Dela Cruz | L95: Very good, light scratches on hardware. Size 39 EU | M95: Dust bag, Box, Receipt, Felt | N95: instagram | O95: walk_in | P95: 45318.612 | Q95: 45335.694 | R95: 45362.74 | S95: Enrique Ocampo | T95: full_payment | V95: 45363.769 | W95: 45375.49
A96: 02238267 | B96: Chanel | C96: 24C Hook Card Holder Micro Bag | D96: Small Leather Goods | E96: Fuchsia Pink Iridescent Mirror Goatskin | F96: Goatskin Silver | H96: 52300 | I96: 13000 | J96: 39300 | K96: Frances Villanueva | L96: Brand new, never used, complete with tags. Microchip present | M96: Dust bag | N96: facebook | O96: drop_off | P96: 45342.601 | Q96: 45357.497 | R96: 45363.497 | S96: Maria Panlilio | T96: full_payment | V96: 45365.775 | W96: 45382.781
A97: 19443771 | B97: Loewe | C97: Font Medium Tote Bag | D97: Tote | E97: Light Blue Raffia Canvas | F97: Silver | H97: 76300 | I97: 13000 | J97: 63300 | K97: Rafael Laurel | L97: Very good, light scratches on hardware | M97: Dust bag, Box | N97: tiktok | O97: walk_in | P97: 45310.499 | Q97: 45333.599 | R97: 45363.798 | S97: Gabriel Escudero | T97: full_payment | V97: 45363.84 | W97: 45381.708
A98: 47061051 | B98: Louis Vuitton | C98: Odeon PM Monogram Canvas Shoulder Bag | D98: Shoulder Bag | G98: FL0221 | H98: 97200 | I98: 13000 | J98: 84200 | K98: Michelle Aquino | L98: Pristine, no visible signs of use | M98: Dust bag, Box | N98: walk_in | O98: walk_in | P98: 45311.64 | Q98: 45331.542 | R98: 45367.733 | S98: Sofia Domingo | T98: full_payment | V98: 45368.707 | W98: 45385.659
A99: 85354811 | B99: Marco de Vincenzo | C99: Satin Furr | D99: Shoes | E99: Pink Fringed Slingback Heels | H99: 29200 | I99: 10000 | J99: 19200 | K99: Ana Tan | L99: Excellent, very light wear on corners. Size 35 Eu | M99: Dust bag, Box, Receipt | N99: walk_in | O99: pickup | P99: 45289.748 | Q99: 45308.612 | R99: 45368.668 | S99: Nicole Gonzales | T99: full_payment | V99: 45369.678 | W99: 45385.668
A100: 90848827 | B100: Hugo Boss | C100: Jersey Polo Shirt | D100: Clothing | E100: Navy/Dark Blue for Men | H100: 13000 | I100: 6000 | J100: 7000 | K100: Eduardo Co | L100: Excellent, very light wear on corners. Size M | M100: Tags | N100: walk_in | O100: pickup | P100: 45333.666 | Q100: 45356.464 | R100: 45373.502 | S100: Bea Castro | T100: full_payment | V100: 45374.443 | W100: 45387.632
...

Sheet Current Stock
A1: Barcode | B1: Brand | C1: Model | D1: Category | E1: Colour / Material | F1: Price | G1: Markup | H1: Consignor Payout | I1: Status | J1: Consignor | K1: Condition | L1: Intake At | M1: Listed At | N1: Layaway Buyer | O1: Layaway Months | P1: Layaway Total Due | Q1: Paid So Far
A2: 19010363 | B2: Hermes | C2: Zipengo Gold PM | D2: Wallet | E2: Evercolor Leather | F2: 109700 | G2: 18000 | H2: 91700 | I2: Available | J2: Angelica Andrada | K2: Pristine, no visible signs of use | L2: 46192.683 | M2: 46214.608
A3: 40011579 | B3: Celine | C3: Classic Box | D3: Shoulder Bag | E3: Brown Smooth Calfskin Leather Shoulder Bag | F3: 86800 | G3: 13000 | H3: 73800 | I3: Available | J3: Yasmin Garcia | K3: Pristine, no visible signs of use | L3: 46190.68 | M3: 46214.629
A4: 52246587 | B4: Chanel | C4: Classic Double Flap Maxi Metallic | D4: Shoulder Bag | E4: Caviar Leather | F4: 322600 | G4: 38712 | H4: 283888 | I4: Available | J4: Patricia Pascual | K4: Very good, light scratches on hardware | L4: 46192.469 | M4: 46214.676
A5: 00863803 | B5: Fendi | C5: First Small Nappa | D5: Handbag | E5: Shiny Torto Dark Beige Smooth Calfskin Leather | F5: 144300 | G5: 18000 | H5: 126300 | I5: Available | J5: Ramon Javier | K5: Excellent, very light wear on corners | L5: 46211.633 | M5: 46222.547
A6: 99430203 | B6: Chanel | C6: Classic Double Flap | D6: Shoulder Bag | E6: Black Chevron Caviar Leather | F6: 457000 | G6: 54840 | H6: 402160 | I6: Available | J6: Eduardo Co | K6: Very good, light scratches on hardware | L6: 46201.696 | M6: 46222.555
A7: 75461691 | B7: Louis Vuitton | C7: Alma BB | D7: Handbag | E7: Damier Ebene Canvas | F7: 101200 | G7: 18000 | H7: 83200 | I7: Available | J7: Iris Navarro | K7: Pristine, no visible signs of use. Microchip present | L7: 46218.736 | M7: 46229.533
A8: 30156347 | B8: Chanel | C8: 19 Small | D8: Handbag | E8: Light Pink Quilted Lambskin Leather | F8: 305800 | G8: 36696 | H8: 269104 | I8: Available | J8: Paolo Laurel | K8: Very good, light scratches on hardware | L8: 46210.766 | M8: 46233.526
A9: 20485947 | B9: Hermes | C9: Picotin Micro Lucky Daisy | D9: Tote | E9: Nata Swift Leather | F9: 175600 | G9: 18000 | H9: 157600 | I9: Reserved (layaway) | J9: Marco Aguilar | K9: Good, visible wear on corners and handles | L9: 46224.724 | M9: 46239.573 | N9: Danica Mendoza | O9: 3 | P9: 180868 | Q9: 45217
A10: 06437947 | B10: Chanel | C10: Boy Galuchat Mini Flap Bag | D10: Shoulder Bag | E10: White Quilted Lambskin Leather | F10: 233000 | G10: 27960 | H10: 205040 | I10: Available | J10: Veronica Domingo | K10: Brand new, never used, complete with tags | L10: 46227.475 | M10: 46240.488
A11: 35363899 | B11: Hermes | C11: Evelyne 16 TPM | D11: Handbag | E11: Gold Epsom Leather | F11: 291000 | G11: 34920 | H11: 256080 | I11: Reserved (layaway) | J11: Pauline Valdez | K11: Good, visible wear on corners and handles | L11: 46231.618 | M11: 46241.67 | N11: Michelle Zamora | O11: 2 | P11: 296820 | Q11: 98940
A12: 12063547 | B12: Givenchy | C12: White Rubber Pool Slides 41 EU | D12: Shoes | F12: 24000 | G12: 10000 | H12: 14000 | I12: Available | J12: Teresa Gatchalian | K12: Good, visible wear on corners and handles | L12: 46234.72 | M12: 46243.701
A13: 91346235 | B13: Hermes | C13: Mini Jypsiere | D13: Handbag | E13: Gris Meyer Evercolor Leather | F13: 703400 | G13: 84408 | H13: 618992 | I13: Available | J13: Rica Mercado | K13: Good, visible wear on corners and handles | L13: 46221.751 | M13: 46244.518
A14: 17371963 | B14: Goyard | C14: Saint Louis PM Gray | D14: Handbag | E14: Goyardine Canvas | F14: 137900 | G14: 18000 | H14: 119900 | I14: Available | J14: Jericho Castro | K14: Brand new, never used, complete with tags | L14: 46224.59 | M14: 46248.537
A15: 67164987 | B15: Chanel | C15: 19 Wallet On Chain | D15: Crossbody | F15: 246300 | G15: 29556 | H15: 216744 | I15: Available | J15: Christian Aquino | K15: Pristine, no visible signs of use. Microchip present | L15: 46240.542 | M15: 46251.488
A16: 74464827 | B16: Louis Vuitton | C16: City Keepall Shoulder Bag | D16: Shoulder Bag | E16: Monogram Eclipse Canvas | F16: 109600 | G16: 18000 | H16: 91600 | I16: Available | J16: Camille Lopez | K16: Good, visible wear on corners and handles. Microchip present | L16: 46236.548 | M16: 46251.557
A17: 68030523 | B17: Stuart Weitzman | C17: Leather White Sneakers 36.5 EU(23.3 cm) | D17: Shoes | F17: 13600 | G17: 6000 | H17: 7600 | I17: Available | J17: Paolo Domingo | K17: Very good, light scratches on hardware | L17: 46242.763 | M17: 46252.68
A18: 20453179 | B18: Hermes | C18: Picotin Micro | D18: Tote | E18: Black Ostrich Leather | F18: 658600 | G18: 79032 | H18: 579568 | I18: Available | J18: Lara Valdez | K18: Excellent, very light wear on corners | L18: 46233.569 | M18: 46254.423
A19: PMS-CONS-2026-00074 | B19: Gucci | C19: Super Mini Dionysus GG Supreme Canvas | D19: Shoulder Bag | F19: 57500 | G19: 13000 | H19: 44500 | I19: Available | J19: Miguel Santos | K19: Pristine, no visible signs of use | L19: 46244.547 | M19: 46255.466
A20: 62794555 | B20: Hermes | C20: Evelyne TPM | D20: Handbag | E20: Etoupe Taurillon Clemence Leather | F20: 204900 | G20: 24588 | H20: 180312 | I20: Available | J20: Jessa Panlilio | K20: Excellent, very light wear on corners | L20: 46241.64 | M20: 46256.6
A21: 58811963 | B21: Christian Dior | C21: Essenstial Tote Bag Small | D21: Tote | E21: Black Archicannage Quilted Calfskin Leather | F21: 151400 | G21: 18000 | H21: 133400 | I21: Available | J21: Carla Pascual | K21: Pristine, no visible signs of use | L21: 46240.589 | M21: 46257.574
A22: 03068731 | B22: Christian Dior | C22: Walk'n'Dior Sneakers | D22: Shoes | E22: Beige Oblique Embroidered Cotton Motif | F22: 52300 | G22: 13000 | H22: 39300 | I22: Available | J22: Bianca Mercado | K22: Very good, light scratches on hardware. Size 37 Eu | L22: 46235.741 | M22: 46257.614
A23: 50845755 | B23: Chanel | C23: Trendy Wallet on Chain(WOC) Black Lambskin Leather | D23: Crossbody | E23: Light | F23: 187300 | G23: 18000 | H23: 169300 | I23: Available | J23: Pauline Valdez | K23: Excellent, very light wear on corners | L23: 46241.475 | M23: 46258.472
A24: 82230843 | B24: Prada | C24: Re-Nylon Demi Lune Bandoliera Crossbody Bag | D24: Crossbody | F24: 87700 | G24: 13000 | H24: 74700 | I24: Available | J24: Erika Rivera | K24: Very good, light scratches on hardware | L24: 46243.705 | M24: 46259.64
A25: 00593979 | B25: Chanel | C25: Gabrielle Clutch with Chain | D25: Clutch | E25: Black Quilted Aged Calfskin Leather | F25: 140900 | G25: 18000 | H25: 122900 | I25: Available | J25: Hannah Roxas | K25: Very good, light scratches on hardware | L25: 46245.726 | M25: 46260.656
A26: 91525435 | B26: Chanel | C26: Classic Coin Case Flap Compact Wallet | D26: Wallet | E26: Iredescent Beige Quilted Caviar Leather | F26: 50200 | G26: 13000 | H26: 37200 | I26: Available | J26: Lara Aquino | K26: Pristine, no visible signs of use | L26: 46242.456 | M26: 46262.5
A27: 16426299 | B27: Hermes | C27: Picotin Lock 18 | D27: Tote | E27: Gold Clemence Leather | F27: 255400 | G27: 30648 | H27: 224752 | I27: Available | J27: Ana Tan | K27: Excellent, very light wear on corners | L27: 46253.688 | M27: 46262.574
A28: 30468411 | B28: Alexander McQueen | C28: New Court Lace Up Shoes | D28: Handbag | E28: White for Women | F28: 18900 | G28: 6000 | H28: 12900 | I28: Available | J28: Bianca Domingo | K28: Excellent, very light wear on corners. Size 39 EU | L28: 46252.505 | M28: 46263.625
A29: 483878991 | B29: Roger Vivier | C29: Trompette Ballerinas | D29: Shoes | E29: Black Shoes Patent Leather | F29: 73100 | G29: 13000 | H29: 60100 | I29: Available | J29: Kim De Leon | K29: Excellent, very light wear on corners. Size 39.5 EU | L29: 46254.619 | M29: 46263.686
A30: 72109371 | B30: Hermes | C30: Heritage Buckle Reversible Belt | D30: Belt | E30: White Epsome Leather | F30: 52300 | G30: 13000 | H30: 39300 | I30: Available | J30: Andrea Laurel | K30: Good, visible wear on corners and handles. Size 85 | L30: 46251.506 | M30: 46265.668
A31: 42370363 | B31: Hermes | C31: Evelyne 16 TPM | D31: Handbag | E31: Etoupe Clemence Leather with Navy Blue Strap | F31: 208400 | G31: 25008 | H31: 183392 | I31: Reserved (layaway) | J31: Pauline Lim | K31: Excellent, very light wear on corners | L31: 46242.747 | M31: 46266.588 | N31: Miguel De Leon | O31: 3 | P31: 214652 | Q31: 53663
A32: 02937659 | B32: Hermes | C32: In The Loop 18 | D32: Handbag | E32: Black/Noir Clemence Leather | F32: 255400 | G32: 30648 | H32: 224752 | I32: Available | J32: Paolo Laurel | K32: Brand new, never used, complete with tags | L32: 46257.659 | M32: 46267.471
A33: 83672379 | B33: Hermes | C33: Kelly 25 Sellier | D33: Handbag | E33: Vert Yucca Epsom Leather | F33: 1355000 | G33: 162600 | H33: 1192400 | I33: Available | J33: Ramon Velasco | K33: Good, visible wear on corners and handles | L33: 46255.604 | M33: 46268.479
A34: 62541883 | B34: Hermes | C34: Evelyne 16 TPM | D34: Handbag | E34: Etoupe Leather Clemence with Navy Blue Strap | F34: 214900 | G34: 25788 | H34: 189112 | I34: Available | J34: Kim Del Rosario | K34: Pristine, no visible signs of use | L34: 46248.442 | M34: 46268.481
A35: 00036923 | B35: Hermes | C35: Mini Herbag Zip 20 | D35: Tote | E35: Ebene Canvas | F35: 285500 | G35: 34260 | H35: 251240 | I35: Available | J35: Pauline Co | K35: Pristine, no visible signs of use | L35: 46249.517 | M35: 46269.481
A36: 86784571 | B36: Christian Dior | C36: My Dior Mini Top Handle Chain Strap Bag | D36: Handbag | E36: Black Cannage Lambskin Leather Light | F36: 151400 | G36: 18000 | H36: 133400 | I36: Available | J36: Kim Santos | K36: Excellent, very light wear on corners | L36: 46253.694 | M36: 46269.66
A37: 78243899 | B37: Hermes | C37: Evelyne III GM Jaune Poussin Clemence | D37: Handbag | E37: Palladium Hardware | F37: 175600 | G37: 18000 | H37: 157600 | I37: Available | J37: Paolo Lim | K37: Excellent, very light wear on corners | L37: 46251.497 | M37: 46270.519
A38: 51353147 | B38: Givenchy | C38: 4G Logo Slide Sandals | D38: Shoes | E38: Black Plague Leather | F38: 36600 | G38: 10000 | H38: 26600 | I38: Available | J38: Paolo Lim | K38: Good, visible wear on corners and handles. Size 38.5 Eu | L38: 46258.548 | M38: 46270.635
A39: 73192251 | B39: Hermes | C39: Constance To Go | D39: Crossbody | E39: Black Epsom Leather | F39: 395400 | G39: 47448 | H39: 347952 | I39: Available | J39: Rica Mercado | K39: Very good, light scratches on hardware | L39: 46255.429 | M39: 46270.649
A40: 21665851 | B40: Chanel | C40: Vintage Camera Bag | D40: Crossbody | E40: Cream Lambskin Leather | F40: 115000 | G40: 18000 | H40: 97000 | I40: Available | J40: Eduardo Zamora | K40: Pristine, no visible signs of use | L40: 46256.578 | M40: 46271.442
A41: 91320635 | B41: Hermes | C41: Lindy 30 | D41: Handbag | E41: Blue Navy Clemence Leather | F41: 345000 | G41: 41400 | H41: 303600 | I41: Available | J41: Carlo Panlilio | K41: Pristine, no visible signs of use | L41: 46249.544 | M41: 46271.449
A42: 99943227 | B42: Louis Vuitton | C42: OnTheGo | D42: Tote | E42: Reserve Monogram Canvas | F42: 81600 | G42: 13000 | H42: 68600 | I42: Available | J42: Hannah Yap | K42: Pristine, no visible signs of use | L42: 46250.574 | M42: 46271.533
A43: 02025019 | B43: Chanel | C43: Reverse Chevron Quilted Top Handle Flap Bag | D43: Shoulder Bag | E43: Lambskin Leather | F43: 177700 | G43: 18000 | H43: 159700 | I43: Available | J43: Marco Aguilar | K43: Pristine, no visible signs of use | L43: 46251.744 | M43: 46271.539
A44: 97357627 | B44: Louis Vuitton | C44: Palm Spring MM | D44: Backpack | E44: Monogram Canvas Backpack | F44: 112900 | G44: 18000 | H44: 94900 | I44: Available | J44: Katrina Javier | K44: Excellent, very light wear on corners | L44: 46247.667 | M44: 46271.578
A45: 48446011 | B45: Hermes | C45: Constance 18 | D45: Handbag | E45: Pink Epsom Leather | F45: 716700 | G45: 86004 | H45: 630696 | I45: Reserved (layaway) | J45: Nicole Lopez | K45: Pristine, no visible signs of use | L45: 46255.585 | M45: 46271.655 | N45: Ana Rivera | O45: 2 | P45: 731034 | Q45: 243678
A46: 38131003 | B46: Hermes | C46: Garden Party Tote Bag(GPT) 36 | D46: Tote | E46: Gold Clemence | F46: 175600 | G46: 18000 | H46: 157600 | I46: Available | J46: Lara Aquino | K46: Very good, light scratches on hardware | L46: 46258.462 | M46: 46272.559
A47: 32431419 | B47: Chanel | C47: Boy New Medium | D47: Shoulder Bag | E47: Yellow Quilted Lambskin Leather | F47: 197800 | G47: 18000 | H47: 179800 | I47: Available | J47: Hannah Velasco | K47: Pristine, no visible signs of use | L47: 46258.417 | M47: 46272.592
A48: 31127355 | B48: Chanel | C48: CC Day Backpack | D48: Backpack | E48: Pink Quilted Caviar Leather Light | F48: 187300 | G48: 18000 | H48: 169300 | I48: Available | J48: Eduardo Co | K48: Excellent, very light wear on corners | L48: 46260.594 | M48: 46272.675
A49: 23110203 | B49: Christian Dior | C49: Booktote | D49: Shoulder Bag | E49: Medium Embroidery and Calfskin Leather Shoulder Bag | F49: 161800 | G49: 18000 | H49: 143800 | I49: Available | J49: Lara Ayala | K49: Excellent, very light wear on corners | L49: 46252.663 | M49: 46273.558
A50: 49146427 | B50: Celine | C50: Burgundy Smooth Calfskin Leather Mini Luggage Tote Bag | D50: Tote | F50: 53900 | G50: 13000 | H50: 40900 | I50: Available | J50: Hannah Roxas | K50: Brand new, never used, complete with tags | L50: 46252.656 | M50: 46273.624
A51: 92500283 | B51: Saint Laurent | C51: Kate Tassel Bag | D51: Handbag | E51: Black Croc-Embossed Leather | F51: 74200 | G51: 13000 | H51: 61200 | I51: Available | J51: Miguel Santos | K51: Very good, light scratches on hardware | L51: 46251.476 | M51: 46273.633
A52: 69753915 | B52: Miu Miu | C52: Cap Toe Silver & White Slip on Shoes | D52: Accessory | F52: 17800 | G52: 6000 | H52: 11800 | I52: Available | J52: Lourdes Tuason | K52: Excellent, very light wear on corners. Size 37.5 EU | L52: 46250.681 | M52: 46273.665
A53: 01527355 | B53: Chanel | C53: Camellia Satin Chocolate Bar Flap Bag Mini | D53: Shoulder Bag | E53: Black Silk Fabric Leather | F53: 144300 | G53: 18000 | H53: 126300 | I53: Available | J53: Vincent Cojuangco | K53: Excellent, very light wear on corners | L53: 46251.483 | M53: 46274.623
A54: 26074427 | B54: Prada | C54: Saffiano Flap Long Wallet | D54: Wallet | E54: Pink | F54: 33000 | G54: 10000 | H54: 23000 | I54: Available | J54: Paolo Laurel | K54: Very good, light scratches on hardware | L54: 46258.758 | M54: 46274.695
A55: 62221115 | B55: Loewe | C55: Amazon Small Stone Blue Soft Graine Calfskin Leather Shoulder Bag | D55: Shoulder Bag | F55: 76300 | G55: 13000 | H55: 63300 | I55: Available | J55: Andrea Laurel | K55: Brand new, never used, complete with tags | L55: 46256.656 | M55: 46275.456
A56: 10647099 | B56: Chanel | C56: Bowling Bag | D56: Handbag | E56: Black Iridescent Calfskin Leather | F56: 165200 | G56: 18000 | H56: 147200 | I56: Available | J56: Rafael Mercado | K56: Pristine, no visible signs of use | L56: 46263.583 | M56: 46275.478
A57: 97922619 | B57: Hermes | C57: Geta | D57: Handbag | E57: Etoupe Chevre Mysore/Goatskin Leather | F57: 367400 | G57: 44088 | H57: 323312 | I57: Available | J57: Jose Aguilar | K57: Excellent, very light wear on corners | L57: 46257.625 | M57: 46276.639
A58: 49623867 | B58: Hermes | C58: 24/24 Mini | D58: Handbag | E58: Rouge H Evercolor Leather | F58: 679900 | G58: 81588 | H58: 598312 | I58: Available | J58: Camille Lopez | K58: Good, visible wear on corners and handles | L58: 46258.464 | M58: 46276.696
A59: 58111803 | B59: Hermes | C59: Kelly 28 Retourne | D59: Handbag | E59: Rouge Tomate Evercolor in | F59: 905000 | G59: 108600 | H59: 796400 | I59: Available | J59: Francis Torres | K59: Excellent, very light wear on corners | L59: 46254.69 | M59: 46276.701
A60: 27081019 | B60: Christian Dior | C60: 30 Montaigne Avenue Bag | D60: Handbag | E60: Gray Box Calfskin Leather | F60: 133800 | G60: 18000 | H60: 115800 | I60: Available | J60: Yasmin Garcia | K60: Excellent, very light wear on corners | L60: 46258.441 | M60: 46277.496
A61: 33697339 | B61: Chanel | C61: Classic Double Flap Medium Black Caviar Leather | D61: Shoulder Bag | E61: Gold Hardware | F61: 501800 | G61: 60216 | H61: 441584 | I61: Available | J61: Hannah Lacson | K61: Brand new, never used, complete with tags | L61: 46257.74 | M61: 46277.658
A62: 34015035 | B62: Hermes | C62: Kelly 28 Retourne | D62: Handbag | E62: Black Togo Leather | F62: 963100 | G62: 115572 | H62: 847528 | I62: Available | J62: Bianca Lim | K62: Very good, light scratches on hardware | L62: 46255.511 | M62: 46277.676
A63: 12194619 | B63: Givenchy | C63: White Rubber Givenchy Pool Slides | D63: Shoes | F63: 24000 | G63: 10000 | H63: 14000 | I63: Available | J63: Marco Aguilar | K63: Brand new, never used, complete with tags. Size 42 EU | L63: 46259.726 | M63: 46277.69
A64: 23743547 | B64: Hermes | C64: Bearn Compact Wallet | D64: Wallet | E64: Rouge Epsom Leather | F64: 107700 | G64: 18000 | H64: 89700 | I64: Available | J64: Carlo Dela Cruz | K64: Excellent, very light wear on corners | L64: 46269.768 | M64: 46278.467
A65: 57842747 | B65: Hermes | C65: Picotin Cargo 18 | D65: Tote | E65: Black Swift | F65: 249800 | G65: 29976 | H65: 219824 | I65: Available | J65: Ramon Sy | K65: Good, visible wear on corners and handles | L65: 46268.626 | M65: 46278.473
A66: 49804091 | B66: Fendi | C66: Peekaboo ISeeU Bag | D66: Handbag | E66: Dark Beige Calfskin Leather | F66: 210600 | G66: 25272 | H66: 185328 | I66: Available | J66: Miguel Santos | K66: Excellent, very light wear on corners | L66: 46269.548 | M66: 46278.49
A67: 55924027 | B67: Hermes | C67: Evelyne 16 Amazone | D67: Handbag | E67: Etoupe Clemence Leather with Navy Blue Strap | F67: 201400 | G67: 24168 | H67: 177232 | I67: Available | J67: Adrian Castillo | K67: Excellent, very light wear on corners | L67: 46257.762 | M67: 46278.54
A68: 76281403 | B68: Hermes | C68: Pilo Pouch | D68: Small Leather Goods | E68: Blue Swift Lambskin Leather | F68: 97200 | G68: 13000 | H68: 84200 | I68: Available | J68: Miguel Santos | K68: Brand new, never used, complete with tags | L68: 46260.459 | M68: 46278.619
A69: 02107963 | B69: Hermes | C69: Kelly Loafers | D69: Shoes | E69: Black | F69: 76300 | G69: 13000 | H69: 63300 | I69: Available | J69: Bianca Mercado | K69: Excellent, very light wear on corners. Size 42 EU | L69: 46264.506 | M69: 46278.706
A70: 19211579 | B70: Saint Laurent | C70: Loulou Shopping Tote Bag | D70: Tote | E70: Black Y Quilted Calfskin Leather | F70: 86800 | G70: 13000 | H70: 73800 | I70: Available | J70: Olivia Lacson | K70: Very good, light scratches on hardware | L70: 46267.689 | M70: 46279.42
A71: 87910203 | B71: Chanel | C71: Business Affinity Flap Bag Medium | D71: Shoulder Bag | E71: Red Caviar Leather | F71: 246300 | G71: 29556 | H71: 216744 | I71: Available | J71: Maria Manalo | K71: Good, visible wear on corners and handles | L71: 46270.622 | M71: 46279.428
A72: 75936827 | B72: Chanel | C72: Classic Double Flap Medium | D72: Shoulder Bag | E72: Black Quilted Lambskin Leather | F72: 479400 | G72: 57528 | H72: 421872 | I72: Available | J72: Iris Ocampo | K72: Good, visible wear on corners and handles. Microchip present | L72: 46269.756 | M72: 46279.534
A73: 94426427 | B73: Hermes | C73: 24/24 Ardoise Bi-color 21 Evercolor/Swift Double Leather and Gold Hardware | D73: Handbag | F73: 669800 | G73: 80376 | H73: 589424 | I73: Available | J73: Jericho Reyes | K73: Very good, light scratches on hardware | L73: 46258.556 | M73: 46279.644
A74: 33396795 | B74: Chanel | C74: Mini Square Pearl Crush | D74: Handbag | E74: Pink Quilted Lambskin Leather | F74: 249800 | G74: 29976 | H74: 219824 | I74: Available | J74: Paolo Lacson | K74: Very good, light scratches on hardware | L74: 46259.61 | M74: 46280.43
A75: 11932475 | B75: Hermes | C75: Constance To Go | D75: Crossbody | E75: Vert Mangrove Evercolor Leather Palladium Hadware | F75: 604600 | G75: 72552 | H75: 532048 | I75: Reserved (layaway) | J75: Paolo Lim | K75: Excellent, very light wear on corners | L75: 46256.647 | M75: 46280.453 | N75: Pauline Soriano | O75: 2 | P75: 616692 | Q75: 205564
A76: 49820475 | B76: Hermes | C76: Mini Lindy Beige Marfa | D76: Handbag | E76: Clemence Leather | F76: 679900 | G76: 81588 | H76: 598312 | I76: Available | J76: Nicole Lopez | K76: Excellent, very light wear on corners | L76: 46261.497 | M76: 46280.501
A77: 57808955 | B77: Hermes | C77: Neo Ankle Boots Noir | D77: Shoes | E77: Calfskin Leather | F77: 73000 | G77: 13000 | H77: 60000 | I77: Available | J77: Kim Santos | K77: Excellent, very light wear on corners. Size 44.5 EU | L77: 46258.465 | M77: 46280.583
A78: 05949243 | B78: Chanel | C78: 19 Maxi | D78: Handbag | E78: Caramel Lambskin Leather | F78: 313500 | G78: 37620 | H78: 275880 | I78: Available | J78: Trisha Dela Cruz | K78: Good, visible wear on corners and handles. Microchip present | L78: 46264.533 | M78: 46280.639
A79: 54495291 | B79: Chloe | C79: Raina Snow Ankle Boots | D79: Shoes | F79: 24000 | G79: 10000 | H79: 14000 | I79: Available | J79: Katrina Ayala | K79: Excellent, very light wear on corners. Size 39 | L79: 46263.515 | M79: 46281.444
A80: 88602683 | B80: Hermes | C80: Bearn Bifold | D80: Wallet | E80: Etoupe Epsom Leather | F80: 268600 | G80: 32232 | H80: 236368 | I80: Available | J80: Eduardo Co | K80: Pristine, no visible signs of use | L80: 46262.569 | M80: 46281.528
A81: 77332027 | B81: Gucci | C81: Marmont Wallet Bi-color GG Supreme Canvas | D81: Wallet | F81: 27200 | G81: 10000 | H81: 17200 | I81: Available | J81: Teresa Gatchalian | K81: Very good, light scratches on hardware | L81: 46261.679 | M81: 46281.553
A82: 49879611 | B82: Chanel | C82: Mini Square | D82: Handbag | E82: Black Quilted Lambskin Leather | F82: 279900 | G82: 33588 | H82: 246312 | I82: Available | J82: Bea Ramos | K82: Excellent, very light wear on corners. Microchip present | L82: 46257.703 | M82: 46281.581
A83: 08869947 | B83: Loewe | C83: Puzzle Bag Mini | D83: Handbag | E83: Taupe Calfskin Leather | F83: 107700 | G83: 18000 | H83: 89700 | I83: Available | J83: Ana Lim | K83: Pristine, no visible signs of use | L83: 46264.558 | M83: 46281.67
A84: 97169211 | B84: Prada | C84: Vitello Phenix Hobo Bag | D84: Shoulder Bag | E84: Black Pebbled Calfskin Leather | F84: 50200 | G84: 13000 | H84: 37200 | I84: Available | J84: Ramon Sy | K84: Pristine, no visible signs of use | L84: 46271.768 | M84: 46282.424
A85: 34648123 | B85: Hermes | C85: Bouncing Crew Sneakers | D85: Shoes | F85: 52300 | G85: 13000 | H85: 39300 | I85: Available | J85: Eduardo Zamora | K85: Brand new, never used, complete with tags. Size 37.5 EU | L85: 46264.458 | M85: 46282.514
A86: 46042171 | B86: Hermes | C86: Mini Lindy 2 Black Clemence Leather | D86: Handbag | E86: Gold Hardware | F86: 681000 | G86: 81720 | H86: 599280 | I86: Reserved (layaway) | J86: Andrea Ong | K86: Very good, light scratches on hardware | L86: 46265.658 | M86: 46282.523 | N86: Iñigo Panlilio | O86: 3 | P86: 701430 | Q86: 175357.5
A87: 01006651 | B87: Chanel | C87: Mini Rectangle Pearl Crush | D87: Handbag | E87: Light Purplish Gray Lambskin Leather | F87: 249800 | G87: 29976 | H87: 219824 | I87: Available | J87: Paolo Lim | K87: Excellent, very light wear on corners. Microchip present | L87: 46259.647 | M87: 46282.673
A88: 11918467 | B88: Chanel | C88: Gabrielle Small Crossbody Bag | D88: Crossbody | E88: Metallic Lambskin Leather | F88: 146300 | G88: 18000 | H88: 128300 | I88: Available | J88: Rafael Tomas | K88: Excellent, very light wear on corners | L88: 46259.498 | M88: 46283.476
A89: 28724539 | B89: Hermes | C89: Garden Party 36 | D89: Tote | E89: Veau Negonda Leather | F89: 210600 | G89: 25272 | H89: 185328 | I89: Available | J89: Paolo Laurel | K89: Pristine, no visible signs of use | L89: 46270.756 | M89: 46283.476
A90: 24220987 | B90: Louis Vuitton | C90: Low Key Hobo PM Black Grained Calfskin Leather Gold Hardware | D90: Shoulder Bag | F90: 166200 | G90: 18000 | H90: 148200 | I90: Available | J90: Miguel Santos | K90: Excellent, very light wear on corners. Microchip present | L90: 46261.5 | M90: 46283.482
A91: 95570235 | B91: Hermes | C91: Herbag Messenger 39 | D91: Tote | E91: Black Military Toile Vache Hunter | F91: 289000 | G91: 34680 | H91: 254320 | I91: Available | J91: Andrea Ong | K91: Pristine, no visible signs of use | L91: 46262.755 | M91: 46283.505
A92: 54897211 | B92: Hermes | C92: Lindy 26 | D92: Handbag | E92: Blue De Malte Clemence Leather &amp; | F92: 434600 | G92: 52152 | H92: 382448 | I92: Available | J92: Miguel Santos | K92: Excellent, very light wear on corners | L92: 46268.641 | M92: 46283.551
A93: 57143355 | B93: Rolex | C93: Oyster Perpetual Datejust White Roman Numeral Dial Two Tone Jubilee Bracelet 26 mm Ref. No. 69173 | D93: Watch | F93: 457000 | G93: 54840 | H93: 402160 | I93: Available | J93: Carla Panlilio | K93: Excellent, very light wear on corners | L93: 46272.778 | M93: 46283.676
A94: 51108923 | B94: Chanel | C94: Grand Shopping Tote Bag | D94: Tote | E94: Black Quilted Caviar Leather | F94: 195500 | G94: 18000 | H94: 177500 | I94: Available | J94: Zara Domingo | K94: Excellent, very light wear on corners | L94: 46269.72 | M94: 46283.693
A95: 09697851 | B95: Hermes | C95: Herbag Mini | D95: Tote | E95: Rouge Canvas | F95: 294600 | G95: 35352 | H95: 259248 | I95: Reserved (layaway) | J95: Kristine Tuason | K95: Very good, light scratches on hardware | L95: 46265.492 | M95: 46284.456 | N95: Adrian De Leon | O95: 3 | P95: 303438 | Q95: 75859.5
A96: 92749371 | B96: Hermes | C96: Evelyne PM | D96: Handbag | E96: Rouge Clemence Leather | F96: 294600 | G96: 35352 | H96: 259248 | I96: Reserved (layaway) | J96: Miguel Santos | K96: Very good, light scratches on hardware | L96: 46274.705 | M96: 46284.53 | N96: Lara Dela Cruz | O96: 2 | P96: 300492 | Q96: 100164
A97: 86521915 | B97: Hermes | C97: Evelyne TPM | D97: Handbag | E97: Gold Taurillon Clemence Leather | F97: 229500 | G97: 27540 | H97: 201960 | I97: Available | J97: Zara Ong | K97: Excellent, very light wear on corners | L97: 46272.714 | M97: 46284.535
A98: 87301947 | B98: Hermes | C98: Garden Party 30 | D98: Tote | E98: Plomb Negonda Leather | F98: 305800 | G98: 36696 | H98: 269104 | I98: Available | J98: Hannah Roxas | K98: Excellent, very light wear on corners | L98: 46261.781 | M98: 46284.562
A99: 59763771 | B99: Chanel | C99: Fancy Wallet on Chain WOC Dark Pink Top Stitched Embroidered Lambskin Leather | D99: Crossbody | E99: Silver Hardware | F99: 154700 | G99: 18000 | H99: 136700 | I99: Available | J99: Jose Lopez | K99: Pristine, no visible signs of use | L99: 46265.781 | M99: 46284.594
A100: 45523515 | B100: Louis Vuitton | C100: Nano Alma | D100: Crossbody | E100: Monogram Candy Factory Canvas Crossbody Bag | F100: 167000 | G100: 18000 | H100: 149000 | I100: Available | J100: Ana Lim | K100: Very good, light scratches on hardware. Microchip present | L100: 46271.707 | M100: 46284.628
...

Sheet Closed Items
A1: Barcode | B1: Brand | C1: Model | D1: Category | E1: Price | F1: Outcome | G1: Consignor | H1: Intake At | I1: Closed At
A2: 34080571 | B2: Chanel | C2: Classic Double Flap Jumbo | D2: Shoulder Bag | E2: 313500 | F2: Closed – Failed authentication | G2: Rica Mercado | H2: 45446.488 | I2: 45458.66
A3: 06604859 | B3: Gucci | C3: Dionysus Mini Shoulder Bag | D3: Shoulder Bag | E3: 62500 | F3: Closed – Rejected | G3: Gabriel Garcia | H3: 45597.578 | I3: 45609.456
A4: 00970299 | B4: Hermes | C4: Mykonos Rubber Sandals | D4: Shoes | E4: 36600 | F4: Closed – Rejected | G4: Miguel Santos | H4: 45947.71 | I4: 45954.455
A5: 47592251 | B5: Chanel | C5: Boy Long Wallet | D5: Wallet | E5: 71100 | F5: Closed – Failed authentication | G5: Francis Aquino | H5: 45608.619 | I5: 45619.558
A6: 55692603 | B6: Fendi | C6: All | D6: Tote | E6: 59100 | F6: Closed – Rejected | G6: Paolo Laurel | H6: 46081.704 | I6: 46088.687
A7: 97499707 | B7: Hermes | C7: Mini Click Kelly Bracelet PM | D7: Jewelry | E7: 65900 | F7: Closed – Rejected | G7: Luis Andrada | H7: 45279.539 | I7: 45288.557
A8: 92745531 | B8: Louis Vuitton | C8: Alma PM | D8: Handbag | E8: 86800 | F8: Closed – Failed authentication | G8: Iñigo Soriano | H8: 45351.582 | I8: 45362.735
A9: 031200827 | B9: Loewe | C9: Compact Hammock Bag Large | D9: Handbag | E9: 83100 | F9: Closed – Failed authentication | G9: Yasmin Garcia | H9: 45710.438 | I9: 45713.729
A10: 70628411 | B10: Balenciaga | C10: Arena Giant Continental Wallet | D10: Wallet | E10: 34500 | F10: Closed – Failed authentication | G10: Paolo Laurel | H10: 46275.581 | I10: 46286.733
A11: 36154939 | B11: Christian Louboutin | C11: Louboutin Black Suede Hidden Platform Pumps Heels | D11: Shoes | E11: 22000 | F11: Closed – Failed authentication | G11: Carlo Madrigal | H11: 45680.544 | I11: 45690.678
A12: 69112123 | B12: Gucci | C12: Mini Tote Bag | D12: Tote | E12: 71100 | F12: Closed – Rejected | G12: Mika Manalo | H12: 45426.476 | I12: 45438.708
A13: 64390459 | B13: Saint Laurent | C13: LouLou Shoulder Bag | D13: Shoulder Bag | E13: 97200 | F13: Closed – Rejected | G13: Miguel Santos | H13: 46247.649 | I13: 46257.782
... A26: 32812859 | B26: Chanel | C26: CC Kelly Small | D26: Handbag | E26: 328200 | F26: Closed – Rejected | G26: Nicole Ayala | H26: 46195.713 | I26: 46202.681

Sheet Historical Sales
A1: Sale Date | B1: Brand | C1: Category | D1: Model | E1: Quantity | F1: Revenue | G1: Barcode | H1: Source
A2: 45202 | B2: Hermes | C2: Jewelry | D2: Rivale Double Tour Croc XS Bracelet Palladium Hardware | E2: 1 | F2: 46000 | G2: 98763835 | H2: Mock history from client catalog (price in markup-rule gap)
A3: 45225 | B3: Louis Vuitton | C3: Small Leather Goods | D3: Charms Card Holder | E3: 1 | F3: 36600 | G3: 23405115 | H3: Mock history from client catalog (price in markup-rule gap)
A4: 45231 | B4: Louis Vuitton | C4: Small Leather Goods | D4: Pochette Key Cles Pouch | E4: 1 | F4: 25100 | G4: 93491515 | H4: Mock history from client catalog (price in markup-rule gap)
A5: 45241 | B5: Gucci | C5: Crossbody | D5: GG Marmont Small Camera Bag | E5: 1 | F5: 45000 | G5: 69305659 | H5: Mock history from client catalog (price in markup-rule gap)
A6: 45256 | B6: Prada | C6: Small Leather Goods | D6: 1MC208 Portacarte Card Holder | E6: 1 | F6: 24000 | G6: 07188283 | H6: Mock history from client catalog (price in markup-rule gap)
A7: 45261 | B7: Gucci | C7: Clutch | D7: Supreme Floral Canvas Zip Clutch | E7: 1 | F7: 23000 | G7: 27057467 | H7: Mock history from client catalog (price in markup-rule gap)
A8: 45264 | B8: Prada | C8: Tote | D8: Daino Vitello Braided Handle Open Tote Bag | E8: 1 | F8: 41800 | G8: 24941115 | H8: Mock history from client catalog (price in markup-rule gap)
A9: 45274 | B9: Prada | C9: Crossbody | D9: Wallet On Chain | E9: 1 | F9: 36600 | G9: 72143675 | H9: Mock history from client catalog (price in markup-rule gap)
A10: 45277 | B10: Fendi | C10: Clothing | D10: Logo Print Two Color Checkered Hoodie | E10: 1 | F10: 49100 | G10: 05299515 | H10: Mock history from client catalog (price in markup-rule gap)
A11: 45284 | B11: Prada | C11: Handbag | D11: Promenade Bag Medium | E11: 1 | F11: 48100 | G11: 07597115 | H11: Mock history from client catalog (price in markup-rule gap)
A12: 45286 | B12: Chanel | C12: Small Leather Goods | D12: Flap Card Holder | E12: 1 | F12: 41800 | G12: 67459387 | H12: Mock history from client catalog (price in markup-rule gap)
A13: 45288 | B13: Prada | C13: Small Leather Goods | D13: x Universal Studios Frankenstein Heart | E13: 1 | F13: 47100 | G13: 95093563 | H13: Mock history from client catalog (price in markup-rule gap)
... A243: 46302 | B243: Loewe | C243: Shoes | D243: Cloudtilt All White Sneakers | E243: 1 | F243: 49100 | G243: 35631931 | H243: Mock history from client catalog (price in markup-rule gap)

Sheet Consignors
A1: Full Name | B1: Phone | C1: Email | D1: ID Type | E1: Items Consigned
A2: Miguel Santos | B2: 09930668581 | C2: miguel.santos@example.com | D2: passport | E2: 68
A3: Hannah Roxas | B3: 09243372480 | C3: hannah.roxas@example.com | D3: drivers_license | E3: 40
A4: Paolo Laurel | B4: 09469577591 | C4: paolo.laurel@example.com | D4: drivers_license | E4: 37
A5: Camille Lopez | B5: 09998226147 | C5: camille.lopez@example.com | D5: passport | E5: 27
A6: Lara Aquino | B6: 09355859675 | C6: lara.aquino@example.com | D6: passport | E6: 25
A7: Marco Aguilar | B7: 09825252642 | C7: marco.aguilar@example.com | D7: drivers_license | E7: 18
A8: Adrian Castillo | B8: 09829293402 | C8: adrian.castillo@example.com | D8: passport | E8: 15
A9: Miguel Javier | B9: 09103567620 | C9: miguel.javier@example.com | D9: drivers_license | E9: 15
A10: Paolo Lim | B10: 09947657215 | C10: paolo.lim@example.com | D10: umid | E10: 15
A11: Andrea Laurel | B11: 09717117215 | C11: andrea.laurel@example.com | D11: philsys_id | E11: 12
A12: Luis Andrada | B12: 09870586376 | C12: luis.andrada@example.com | D12: drivers_license | E12: 11
A13: Rica Mercado | B13: 09408107872 | C13: rica.mercado@example.com | D13: passport | E13: 10
... A279: Jasmine Domingo | B279: 09837409429 | C279: jasmine.domingo@example.com | D279: philsys_id | E279: 1

Sheet Catalog
A1: Barcode | B1: Vendor (original) | C1: Item Name (original) | D1: Price (original) | E1: Brand | F1: Category | G1: Model | H1: Colour / Material | I1: Hardware | J1: Date Code | K1: Size | L1: Microchip | M1: Used As
A2: 70428475 | B2: Chanel | C2: Chanel Boy Chevron Wallet on Chain in Peach Caviar Leather and Light Gold Hardware Microchip | D2: 187300 | E2: Chanel | F2: Crossbody | G2: Boy Chevron Wallet on Chain | H2: Peach Caviar Leather | I2: Light Gold | L2: Yes | M2: Sold (full record)
A3: 57010491 | B3: Chanel | C3: Chanel Classic Double Flap Medium in Black Caviar Leather and Gold Hardware Microchip | D3: 513000 | E3: Chanel | F3: Shoulder Bag | G3: Classic Double Flap Medium | H3: Black Caviar Leather | I3: Gold | L3: Yes | M3: Sold (full record)
A4: 64305211 | B4: Chanel | C4: Chanel CC Filigree Wallet on Chain in Beige and Black Caviar Leather and Gold Hardware Series 30 | D4: 199000 | E4: Chanel | F4: Crossbody | G4: CC Filigree Wallet on Chain | H4: Beige | I4: Gold | J4: Series 30 | M4: Sold (full record)
A5: 16201787 | B5: Chanel | C5: Chanel Turn Lock Wallet on Chain (WOC) in Black Caviar Leather Gold Hardware Microchip (AE****E4) | D5: 261000 | E5: Chanel | F5: Crossbody | G5: Turn Lock Wallet on Chain | H5: Black Caviar Leather | I5: Gold | L5: Yes | M5: Sold (full record)
A6: PMC-CONS-2026-00036 | B6: Chanel | C6: Chanel 25 Mini in Black Caviar Leather Shiny Gold Hardware Microchip (C5****81) | D6: 501800 | E6: Chanel | F6: Handbag | G6: 25 Mini | H6: Black Caviar Leather Shiny | I6: Shiny Gold | L6: Yes | M6: In stock – Available
A7: 39756347 | B7: Chanel | C7: Chanel Classic Double Flap Jumbo in Black Quilted Caviar Leather and Gold Hardware Series 27 | D7: 401000 | E7: Chanel | F7: Shoulder Bag | G7: Classic Double Flap Jumbo | H7: Black Quilted Caviar Leather | I7: Gold | J7: Series 27 | M7: Sold (full record)
A8: 53853499 | B8: Chanel | C8: Chanel Shopping Fever Tote Bag in Silver Metallic Caviar Leather and Silver Hardware Series 20 | D8: 86800 | E8: Chanel | F8: Tote | G8: Shopping Fever Tote Bag | H8: Silver Metallic Caviar Leather | I8: Silver | J8: Series 20 | M8: Closed – Rejected
A9: 57929787 | B9: Chanel | C9: Chanel Classic Double Flap in Dark Gray Caviar Leather Gold Hardware (Series 26) | D9: 391900 | E9: Chanel | F9: Shoulder Bag | G9: Classic Double Flap | H9: Dark Gray Caviar Leather | I9: Gold | J9: Series 26 | M9: Not used
A10: 18362939 | B10: Chanel | C10: Chanel Petite Shopping Tote Bag (PST) in Dark Beige Caviar Leather Gold Hardware (Series 8) | D10: 97200 | E10: Chanel | F10: Tote | G10: Petite Shopping Tote Bag | H10: Dark Beige Caviar Leather | I10: Gold | J10: Series 8 | M10: Sold (full record)
A11: 75838779 | B11: Chanel | C11: Chanel Classic Double Flap Jumbo in Red Quilted Caviar Leather and Silver Hardware Series 16 | D11: 335900 | E11: Chanel | F11: Shoulder Bag | G11: Classic Double Flap Jumbo | H11: Red Quilted Caviar Leather | I11: Silver | J11: Series 16 | M11: Sold (full record)
A12: 92724283 | B12: Chanel | C12: Chanel Paris Limited Edition Double Flap Bag Medium in Black Lambskin Leather Mix Hardware (Series 3) | D12: 210600 | E12: Chanel | F12: Shoulder Bag | G12: Paris Limited Edition Double Flap Bag Medium | H12: Black Lambskin Leather | I12: Mix | J12: Series 3 | M12: Sold (full record)
A13: 89119291 | B13: Chanel | C13: Chanel Classic Double Flap Bag Small in Black Caviar Leather Gold Hardware Microchip CX****KJ | D13: 602600 | E13: Chanel | F13: Shoulder Bag | G13: Classic Double Flap Bag Small | H13: Black Caviar Leather | I13: Gold | L13: Yes | M13: In stock – Available
A14: 14130235 | B14: Chanel | C14: Chanel Wallet on Chain (WOC) in Black Quilted Caviar Leather and Gold Hardware Series 29 | D14: 193200 | E14: Chanel | F14: Crossbody | G14: Wallet on Chain | H14: Black Quilted Caviar Leather | I14: Gold | J14: Series 29 | M14: Sold (full record)
A15: 18047547 | B15: Chanel | C15: Chanel Classic Mini Rectangular Flap Bag in Black Lambskin Leather Silver Hardware (Series 25) | D15: 277800 | E15: Chanel | F15: Shoulder Bag | G15: Classic Mini Rectangular Flap Bag | H15: Black Lambskin Leather | I15: Silver | J15: Series 25 | M15: Sold (full record)
A16: 18694971 | B16: Chanel | C16: Chanel CC You Flap Bag in Dark Brown Caviar Leather Shiny Gold Hardware (Microchip) | D16: 401000 | E16: Chanel | F16: Shoulder Bag | G16: CC You Flap Bag | H16: Dark Brown Caviar Leather Shiny | I16: Shiny Gold | L16: Yes | M16: Not used
A17: PMS-CONS-2026-00020 | B17: Chanel | C17: Chanel Classic Double Flap Medium in Black Caviar Leather Silver Hardware (Series 18) | D17: 434600 | E17: Chanel | F17: Shoulder Bag | G17: Classic Double Flap Medium | H17: Black Caviar Leather | I17: Silver | J17: Series 18 | M17: Sold (full record)
A18: 35468347 | B18: Chanel | C18: Chanel Wallet on Chain (WOC) in Black Quilted Caviar Leather and Gold Hardware Microchip | D18: 216200 | E18: Chanel | F18: Crossbody | G18: Wallet on Chain | H18: Black Quilted Caviar Leather | I18: Gold | L18: Yes | M18: Not used
A19: PMS-CONS-2026-00073 | B19: Chanel | C19: Chanel Classic Flap Card Holder in White Quilted Caviar Leather and Silver Hardware Series 30 | D19: 52300 | E19: Chanel | F19: Small Leather Goods | G19: Classic Flap Card Holder | H19: White Quilted Caviar Leather | I19: Silver | J19: Series 30 | M19: Sold (full record)
A20: 87910203 | B20: Chanel | C20: Chanel Business Affinity Flap Bag Medium in Red Caviar Leather and Gold Hardware Series 28 | D20: 246300 | E20: Chanel | F20: Shoulder Bag | G20: Business Affinity Flap Bag Medium | H20: Red Caviar Leather | I20: Gold | J20: Series 28 | M20: In stock – Available
A21: 58059579 | B21: Chanel | C21: Chanel Wallet on Chain (WOC) in Black Caviar Leather Silver Hardware Microchip (X9****PL) | D21: 244200 | E21: Chanel | F21: Crossbody | G21: Wallet on Chain | H21: Black Caviar Leather | I21: Silver | L21: Yes | M21: Sold (full record)
A22: 53566523 | B22: Chanel | C22: Chanel Envelope Flap Bag in White Chevron Calfskin Leather and Gold Hardware Series 27 | D22: 144300 | E22: Chanel | F22: Shoulder Bag | G22: Envelope Flap Bag | H22: White Chevron Calfskin Leather | I22: Gold | J22: Series 27 | M22: Sold (full record)
A23: 06365499 | B23: Chanel | C23: Chanel Classic Flap Card Holder in Black Quilted Calfskin Leather and Silver Hardware Series 22 | D23: 38500 | E23: Chanel | F23: Small Leather Goods | G23: Classic Flap Card Holder | H23: Black Quilted Calfskin Leather | I23: Silver | J23: Series 22 | M23: Historical sale (markup gap)
A24: 74417723 | B24: Chanel | C24: Chanel Deauville Tote Bag in Vibrant Yellow Mixed Fibers and Light Gold Hardware Microchip | D24: 175600 | E24: Chanel | F24: Tote | G24: Deauville Tote Bag | H24: Vibrant Yellow Mixed Fibers | I24: Light Gold | L24: Yes | M24: Sold (full record)
A25: 50660923 | B25: Chanel | C25: Chanel Le Boy New Medium in Black Chevron Lambskin Leather and Ruthenium Hardware Series 22 | D25: 277800 | E25: Chanel | F25: Shoulder Bag | G25: Le Boy New Medium | H25: Black Chevron Lambskin Leather | I25: Ruthenium | J25: Series 22 | M25: Sold (full record)
A26: 14550587 | B26: Chanel | C26: Chanel Boy Wallet On Chain in Black Quilted Caviar Leather and Aged Gold Hardware Microchip | D26: 175600 | E26: Chanel | F26: Crossbody | G26: Boy Wallet On Chain | H26: Black Quilted Caviar Leather | I26: Aged Gold | L26: Yes | M26: Sold (full record)
A27: 43233595 | B27: Chanel | C27: Chanel Deauville Bowling Bag Small in Pink Canvas Silver Hardware (Series 20) | D27: 123400 | E27: Chanel | F27: Handbag | G27: Deauville Bowling Bag Small | H27: Pink Canvas | I27: Silver | J27: Series 20 | M27: Sold (full record)
A28: 211543611 | B28: Chanel | C28: Chanel Turn Lock Wallet on Chain (WOC) in Black Caviar Leather Gold Hardware Microchip (P3****83) | D28: 266600 | E28: Chanel | F28: Crossbody | G28: Turn Lock Wallet on Chain | H28: Black Caviar Leather | I28: Gold | L28: Yes | M28: Sold (full record)
A29: 56165691 | B29: Chanel | C29: Chanel Classic Wallet on Chain (WOC) in Black Caviar Leather Silver Hardware Microchip (HJ****5J) | D29: 244200 | E29: Chanel | F29: Crossbody | G29: Classic Wallet on Chain | H29: Black Caviar Leather | I29: Silver | L29: Yes | M29: Sold (full record)
A30: 95962939 | B30: Chanel | C30: Chanel Wallet on Chain (WOC) in Black Caviar Leather and Silver Hardware Microchip (HC****E0) | D30: 244200 | E30: Chanel | F30: Crossbody | G30: Wallet on Chain | H30: Black Caviar Leather | I30: Silver | L30: Yes | M30: Sold (full record)
A31: 60598331 | B31: Chanel | C31: Chanel Classic Wallet on Chain (WOC) in Black Caviar Leather Silver Hardware Series (29****17) | D31: 227400 | E31: Chanel | F31: Crossbody | G31: Classic Wallet on Chain | H31: Black Caviar Leather | I31: Silver | M31: Sold (full record)
A32: 67340603 | B32: Chanel | C32: Chanel Classic Wallet on Chain (WOC) in Black Caviar Leather Gold Hardware Microchip (L6****54) | D32: 233000 | E32: Chanel | F32: Crossbody | G32: Classic Wallet on Chain | H32: Black Caviar Leather | I32: Gold | L32: Yes | M32: Sold (full record)
A33: 89115451 | B33: Chanel | C33: Chanel Classic Wallet on Chain (WOC) in Black Caviar Leather Gold Hardware Microchip (X1***CC) | D33: 238600 | E33: Chanel | F33: Crossbody | G33: Classic Wallet on Chain | H33: Black Caviar Leather | I33: Gold | L33: Yes | M33: Not used
A34: 031509307 | B34: Chanel | C34: Chanel Classic Wallet on Chain (WOC) in Black Caviar Leather Silver Hardware (Series 30****85) | D34: 221800 | E34: Chanel | F34: Crossbody | G34: Classic Wallet on Chain | H34: Black Caviar Leather | I34: Silver | J34: Series 30 | M34: Sold (full record)
A35: 96333371 | B35: Chanel | C35: Chanel 19 Flap Bag Medium in Black Lambskin Leather Mix Hardware (Microchip) | D35: 333800 | E35: Chanel | F35: Shoulder Bag | G35: 19 Flap Bag Medium | H35: Black Lambskin Leather | I35: Mix | L35: Yes | M35: Sold (full record)
A36: 57142843 | B36: Chanel | C36: Chanel Business Affinity Small in Caramel Caviar Leather Light Gold Hardware (Series 30) | D36: 291100 | E36: Chanel | F36: Handbag | G36: Business Affinity Small | H36: Caramel Caviar Leather Light | I36: Light Gold | J36: Series 30 | M36: Sold (full record)
A37: 78368571 | B37: Chanel | C37: Chanel Matelassé Camera Bag in Yellow Calfskin Leather and Gold Hardware Series 26 | D37: 144300 | E37: Chanel | F37: Crossbody | G37: Matelassé Camera Bag | H37: Yellow Calfskin Leather | I37: Gold | J37: Series 26 | M37: Not used
A38: 54465851 | B38: Chanel | C38: Chanel Classic Wallet on Chain (WOC) in Black Caviar Leather in Gold Hardware Microchip (HK****3L) | D38: 238600 | E38: Chanel | F38: Crossbody | G38: Classic Wallet on Chain | H38: Black Caviar Leather in | I38: Gold | L38: Yes | M38: Sold (full record)
A39: 24901179 | B39: Chanel | C39: Chanel Le Boy Small in Black Chevron Lambskin Leather and Silver Hardware Series 22 | D39: 240700 | E39: Chanel | F39: Shoulder Bag | G39: Le Boy Small | H39: Black Chevron Lambskin Leather | I39: Silver | J39: Series 22 | M39: Not used
A40: 95737659 | B40: Chanel | C40: Chanel Medallion Tote Bag in Black Quilted Patent Leather Series 6 | D40: 97000 | E40: Chanel | F40: Tote | G40: Medallion Tote Bag | H40: Black Quilted Patent Leather | J40: Series 6 | M40: Sold (full record)
A41: 14125883 | B41: Chanel | C41: Chanel Le Boy Old Medium in Red Lambskin Leather in Red Aged Gold Hardware (Series 23) | D41: 233000 | E41: Chanel | F41: Shoulder Bag | G41: Le Boy Old Medium | H41: Red Lambskin Leather in Red Aged | I41: Aged Gold | J41: Series 23 | M41: Sold (full record)
A42: 71461947 | B42: Chanel | C42: Chanel Grand Shopping Tote (GST) in Black Quilted Caviar Leather and Gold Hardware Series 13 | D42: 195500 | E42: Chanel | F42: Tote | G42: Grand Shopping Tote | H42: Black Quilted Caviar Leather | I42: Gold | J42: Series 13 | M42: Not used
A43: 50407227 | B43: Chanel | C43: Chanel Classic Mini Rectangular Flap Bag in Pink Chevron Lambskin Leather Light Gold Hardware (Series 27) | D43: 289000 | E43: Chanel | F43: Shoulder Bag | G43: Classic Mini Rectangular Flap Bag | H43: Pink Chevron Lambskin Leather Light | I43: Light Gold | J43: Series 27 | M43: Not used
A44: 02238267 | B44: Chanel | C44: Chanel 24C Hook Card Holder Micro Bag in Fuchsia Pink Iridescent Mirror Goatskin Silver Hardware (Microchip) | D44: 52300 | E44: Chanel | F44: Small Leather Goods | G44: 24C Hook Card Holder Micro Bag | H44: Fuchsia Pink Iridescent Mirror Goatskin | I44: Goatskin Silver | L44: Yes | M44: Sold (full record)
A45: 67198779 | B45: Chanel | C45: Chanel Grand Shopping Tote Bag (GST) in Black Quilted Caviar Leather Gold Hardware (Series 19) | D45: 195500 | E45: Chanel | F45: Tote | G45: Grand Shopping Tote Bag | H45: Black Quilted Caviar Leather | I45: Gold | J45: Series 19 | M45: Sold (full record)
A46: 77721403 | B46: Chanel | C46: Chanel Chevron Drawstring Bucket Bag in Beige Calfskin Leather and Silver Hardware Series 23 | D46: 123400 | E46: Chanel | F46: Handbag | G46: Chevron Drawstring Bucket Bag | H46: Beige Calfskin Leather | I46: Silver | J46: Series 23 | M46: Sold (full record)
A47: 70777659 | B47: Chanel | C47: Chanel Grand Shopping Tote Bag (GST) in Black Quilted Caviar Leather and Gold Hardware (Series 19) | D47: 195500 | E47: Chanel | F47: Tote | G47: Grand Shopping Tote Bag | H47: Black Quilted Caviar Leather | I47: Gold | J47: Series 19 | M47: Sold (full record)
A48: 78601275 | B48: Chanel | C48: Chanel 26 Urban Essential Matthieu Blazy Large Tote Bag in Black Calfskin Leather and Denim Canvas Light Gold Hardware (Microchip) | D48: 647400 | E48: Chanel | F48: Tote | G48: 26 Urban Essential Matthieu Blazy Large Tote Bag | H48: Black Calfskin Leather | I48: Light Gold | L48: Yes | M48: Sold (full record)
A49: 51108923 | B49: Chanel | C49: Chanel Grand Shopping Tote Bag (GST) in Black Quilted Caviar Leather and Gold Hardware Series 17 | D49: 195500 | E49: Chanel | F49: Tote | G49: Grand Shopping Tote Bag | H49: Black Quilted Caviar Leather | I49: Gold | J49: Series 17 | M49: In stock – Available
A50: 92118587 | B50: Chanel | C50: Chanel Wallet on Chain (WOC) in Black Caviar Leather Silver Hardware Microchip(A2****8K) | D50: 229700 | E50: Chanel | F50: Crossbody | G50: Wallet on Chain | H50: Black Caviar Leather | I50: Silver | L50: Yes | M50: Sold (full record)
A51: 02543931 | B51: Chanel | C51: Chanel 25 Hobo Bag Medium in Black Caviar Leather Aged Gold Hardware (Microchip) | D51: 434600 | E51: Chanel | F51: Shoulder Bag | G51: 25 Hobo Bag Medium | H51: Black Caviar Leather Aged | I51: Aged Gold | L51: Yes | M51: Closed – Failed authentication
A52: 79321403 | B52: Chanel | C52: Chanel Classic Wallet on Chan (WOC) in Black Caviar Leather Gold Hardware (Series 29) | D52: 227400 | E52: Chanel | F52: Crossbody | G52: Classic Wallet on Chan | H52: Black Caviar Leather | I52: Gold | J52: Series 29 | M52: Sold (full record)
A53: 06516027 | B53: Chanel | C53: Chanel Grand Shopping Tote Bag (GST) in Black Quilted Caviar Leather Gold Hardware (Series 15***52) | D53: 195500 | E53: Chanel | F53: Tote | G53: Grand Shopping Tote Bag | H53: Black Quilted Caviar Leather | I53: Gold | J53: Series 15 | M53: Sold (full record)
A54: 32812859 | B54: Chanel | C54: Chanel CC Kelly Small in Baby Pink Shinny Calfskin Leather Aged Gold Hardware Microchip(E8****T5) | D54: 328200 | E54: Chanel | F54: Handbag | G54: CC Kelly Small | H54: Baby Pink Shinny Calfskin Leather Aged | I54: Aged Gold | L54: Yes | M54: Closed – Rejected
A55: 13048635 | B55: Chanel | C55: Chanel Grand Shopping Tote Bag (GST) in Black Caviar Leather Silver Hardware (Series 17****92) | D55: 204900 | E55: Chanel | F55: Tote | G55: Grand Shopping Tote Bag | H55: Black Caviar Leather | I55: Silver | J55: Series 17 | M55: Sold (full record)
A56: 60161083 | B56: Chanel | C56: Chanel Classic Doube Flap Jumbo in Black Quilted Caviar Leather and Gold Hardware Series 16 | D56: 277800 | E56: Chanel | F56: Shoulder Bag | G56: Classic Doube Flap Jumbo | H56: Black Quilted Caviar Leather | I56: Gold | J56: Series 16 | M56: Not used
A57: 99345723 | B57: Chanel | C57: Chanel Camellia Emobossed Long Wallet in Peach Pink Lambskin Leather and Silver Hardware Series 15 | D57: 25100 | E57: Chanel | F57: Wallet | G57: Camellia Emobossed Long Wallet | H57: Peach Pink Lambskin Leather | I57: Silver | J57: Series 15 | M57: Not used
A58: 16649787 | B58: Chanel | C58: Chanel 19 Flap Bag Medium in Beige Calfskin Leather with Crochet Trim and Mixed Hardware Series 30 | D58: 277800 | E58: Chanel | F58: Shoulder Bag | G58: 19 Flap Bag Medium | H58: Beige Calfskin Leather with Crochet Trim | I58: Mixed | J58: Series 30 | M58: In stock – Available
A59: 45117243 | B59: Chanel | C59: Chanel Classic Rectangular Mini Flap Bag in Fuchsia Lambskin Leather Light Gold Hardware (Series 21) | D59: 175600 | E59: Chanel | F59: Shoulder Bag | G59: Classic Rectangular Mini Flap Bag | H59: Fuchsia Lambskin Leather Light | I59: Light Gold | J59: Series 21 | M59: In stock – Available
A60: 56750907 | B60: Chanel | C60: Chanel Le Boy Flap Bag Small in Blue Calfskin Leather Light Gold Hardware (Series 24) | D60: 216200 | E60: Chanel | F60: Shoulder Bag | G60: Le Boy Flap Bag Small | H60: Blue Calfskin Leather Light | I60: Light Gold | J60: Series 24 | M60: Sold (full record)
A61: 31127355 | B61: Chanel | C61: Chanel CC Day Backpack in Pink Quilted Caviar Leather Light Gold Hardware (Series 27) | D61: 187300 | E61: Chanel | F61: Backpack | G61: CC Day Backpack | H61: Pink Quilted Caviar Leather Light | I61: Light Gold | J61: Series 27 | M61: In stock – Available
A62: 15103803 | B62: Chanel | C62: Chanel Coco Handle Small in Pink Chevron Quilted Caviar Leather and Light Gold Hardware Series 29 | D62: 289000 | E62: Chanel | F62: Handbag | G62: Coco Handle Small | H62: Pink Chevron Quilted Caviar Leather | I62: Light Gold | J62: Series 29 | M62: Sold (full record)
A63: 49559867 | B63: Chanel | C63: Chanel Large Bowling Bag in Dark Brown Calfskin Leather and Gold Hardware (Microchip) | D63: 513000 | E63: Chanel | F63: Handbag | G63: Large Bowling Bag | H63: Dark Brown Calfskin Leather | I63: Gold | L63: Yes | M63: Sold (full record)
A64: 49421883 | B64: Chanel | C64: Chanel Classic Wallet on Chain in Black Caviar Leather and Gold Hardware Series 29 | D64: 187300 | E64: Chanel | F64: Crossbody | G64: Classic Wallet on Chain | H64: Black Caviar Leather | I64: Gold | J64: Series 29 | M64: In stock – Available
A65: 57704507 | B65: Chanel | C65: Chanel Grand Shopping Tote Bag (GST) in Black Caviar Leather Silver Hardware (Series 19) | D65: 204900 | E65: Chanel | F65: Tote | G65: Grand Shopping Tote Bag | H65: Black Caviar Leather | I65: Silver | J65: Series 19 | M65: Sold (full record)
A66: 15239995 | B66: Chanel | C66: Chanel Classic Double Flap Maxi in Black Quilted Caviar Leather and Gold Hardware Series 15 | D66: 319800 | E66: Chanel | F66: Shoulder Bag | G66: Classic Double Flap Maxi | H66: Black Quilted Caviar Leather | I66: Gold | J66: Series 15 | M66: Sold (full record)
A67: 38368827 | B67: Chanel | C67: Chanel Color Burst Clutch in Lambskin Leather With Black Polished Metal Chain Strap Bag (Microchip) | D67: 175600 | E67: Chanel | F67: Clutch | G67: Color Burst Clutch | H67: Lambskin Leather With Black Polished Metal Chain Strap Bag | L67: Yes | M67: Sold (full record)
A68: 10983739 | B68: Chanel | C68: Chanel 19 Large in Caramel Quilted Lambskin Leather and Mixed Hardware Microchip | D68: 261000 | E68: Chanel | F68: Handbag | G68: 19 Large | H68: Caramel Quilted Lambskin Leather | I68: Mixed | L68: Yes | M68: Sold (full record)
A69: 75034427 | B69: Chanel | C69: Chanel Timeless CC Long Bifold Wallet in White Caviar Leather and Gold Hardware Series 5 | D69: 23000 | E69: Chanel | F69: Wallet | G69: Timeless CC Long Bifold Wallet | H69: White Caviar Leather | I69: Gold | J69: Series 5 | M69: Sold (full record)
A70: 78164539 | B70: Chanel | C70: Chanel 25 Hobo Bag Mini in Black Perforated Calfskin Leather Aged Gold Hardware (Microchip) | D70: 513000 | E70: Chanel | F70: Shoulder Bag | G70: 25 Hobo Bag Mini | H70: Black Perforated Calfskin Leather Aged | I70: Aged Gold | L70: Yes | M70: Sold (full record)
A71: 35976251 | B71: Chanel | C71: Chanel 25 Hobo Bag Mini in Light Green Caviar Leather Shiny Gold Hardware (Microchip) | D71: 501800 | E71: Chanel | F71: Shoulder Bag | G71: 25 Hobo Bag Mini | H71: Light Green Caviar Leather Shiny | I71: Shiny Gold | L71: Yes | M71: Sold (full record)
A72: 10974267 | B72: Chanel | C72: Chanel Timeless Patchwork Single Flap Bag Small in Multicolor Lambskin & Python Leather Aged Gold Hardware (Series 22) | D72: 266600 | E72: Chanel | F72: Shoulder Bag | G72: Timeless Patchwork Single Flap Bag Small | H72: Multicolor Lambskin | I72: Aged Gold | J72: Series 22 | M72: Not used
A73: 06353979 | B73: Chanel | C73: Chanel Tassel Top Handle Bag in Metallic Quilted Caviar Leather Silver Hardware (Series 9) | D73: 97200 | E73: Chanel | F73: Handbag | G73: Tassel Top Handle Bag | H73: Metallic Quilted Caviar Leather | I73: Silver | J73: Series 9 | M73: Sold (full record)
A74: 61199675 | B74: Chanel | C74: Chanel CC Kelly Small in Light Blue Calfskin Leather and Aged Gold Hardware (Microchip) | D74: 350600 | E74: Chanel | F74: Handbag | G74: CC Kelly Small | H74: Light Blue Calfskin Leather | I74: Aged Gold | L74: Yes | M74: Sold (full record)
A75: 66509115 | B75: Chanel | C75: Chanel Coco Handle Small in Black Quilted Caviar Leather and Light Gold Hardware Series 24 | D75: 277800 | E75: Chanel | F75: Handbag | G75: Coco Handle Small | H75: Black Quilted Caviar Leather | I75: Light Gold | J75: Series 24 | M75: Sold (full record)
A76: 65526075 | B76: Chanel | C76: Chanel Boy Old Medium in Black Chevron Calfskin Leather and Aged Gold Hardware Series 26 | D76: 289000 | E76: Chanel | F76: Shoulder Bag | G76: Boy Old Medium | H76: Black Chevron Calfskin Leather | I76: Aged Gold | J76: Series 26 | M76: Sold (full record)
A77: 61184827 | B77: Chanel | C77: Chanel Gabrielle Hobo Bag Small in Sequin Logo Motif Navy Blue/White Mix Hardware (Series 27) | D77: 123400 | E77: Chanel | F77: Shoulder Bag | G77: Gabrielle Hobo Bag Small | H77: Sequin Logo Motif Navy Blue/White | I77: White Mix | J77: Series 27 | M77: Sold (full record)
A78: 32536891 | B78: Chanel | C78: Chanel 19 Small in Black Quilted Lambskin Leather and Mix Hardware Series 31 | D78: 289000 | E78: Chanel | F78: Handbag | G78: 19 Small | H78: Black Quilted Lambskin Leather | I78: Mix | J78: Series 31 | M78: Sold (full record)
A79: 93746747 | B79: Chanel | C79: Chanel Perforated Ultimate Soft Hobo Bag in Black and Silver Hardware Series 12 | D79: 107700 | E79: Chanel | F79: Shoulder Bag | G79: Perforated Ultimate Soft Hobo Bag | H79: Black | I79: Silver | J79: Series 12 | M79: Sold (full record)
A80: 49542715 | B80: Chanel | C80: Chanel Boy North South Flap Bag in Black Quilted Caviar Leather and Aged Gold Hardware Series 28 | D80: 181500 | E80: Chanel | F80: Shoulder Bag | G80: Boy North South Flap Bag | H80: Black Quilted Caviar Leather | I80: Aged Gold | J80: Series 28 | M80: Sold (full record)
A81: 83384123 | B81: Chanel | C81: Chanel 25 Medium in Caramel Caviar Leather Aged Gold Hardware (Microchip) | D81: 513000 | E81: Chanel | F81: Handbag | G81: 25 Medium | H81: Caramel Caviar Leather Aged | I81: Aged Gold | L81: Yes | M81: Not used
A82: 65263419 | B82: Chanel | C82: Chanel 19 Flap Bag Small in Beige Quilted Lambskin Leather and Mixed Hardware Microchip | D82: 311400 | E82: Chanel | F82: Shoulder Bag | G82: 19 Flap Bag Small | H82: Beige Quilted Lambskin Leather | I82: Mixed | L82: Yes | M82: Not used
A83: 81101083 | B83: Chanel | C83: Chanel Boy Zipped Double Zip Around Wallet in Chain in Blue-gray Caviar Leather in Aged Gold Hardware (Series 25) | D83: 146100 | E83: Chanel | F83: Wallet | G83: Boy Zipped Double Zip Around Wallet | H83: Chain in Blue-gray Caviar Leather in Aged | I83: Aged Gold | J83: Series 25 | M83: Not used
A84: 70250555 | B84: Chanel | C84: Chanel Gabrielle Medium in Black Quilted Lambskin Leather Hobo Bag in Black Mix Hardware Series 30 | D84: 218300 | E84: Chanel | F84: Shoulder Bag | G84: Gabrielle Medium | H84: Black Quilted Lambskin Leather Hobo Bag in Black | I84: Black Mix | J84: Series 30 | M84: Sold (full record)
A85: 74814267 | B85: Chanel | C85: Chanel Mini O-case Coin Purse in Black Quilted Patent Leather Ruthenium Hardware Series 19 | D85: 22000 | E85: Chanel | F85: Small Leather Goods | G85: Mini O-case Coin Purse | H85: Black Quilted Patent Leather | I85: Ruthenium | J85: Series 19 | M85: Historical sale (markup gap)
A86: 30567227 | B86: Chanel | C86: Chanel Wallet on Chain in Black Quilted Caviar Leather and Gold Hardware Microchip | D86: 227400 | E86: Chanel | F86: Crossbody | G86: Wallet on Chain | H86: Black Quilted Caviar Leather | I86: Gold | L86: Yes | M86: Not used
A87: 57523771 | B87: Chanel | C87: Chanel Round Clip-on Coin Purse and Airpods Case Set in Metallic Gold Quilted Lambskin Leather and Light Gold Hardware Microchip | D87: 65900 | E87: Chanel | F87: Small Leather Goods | G87: Round Clip-on Coin Purse and Airpods Case Set | H87: Metallic Gold Quilted Lambskin Leather | I87: Light Gold | L87: Yes | M87: In stock – Available
A88: 36105019 | B88: Chanel | C88: Chanel Curvy Mood Hobo Bag in Black Quilted Calfskin Leather and Aged Gold Hardware Microchip | D88: 277800 | E88: Chanel | F88: Shoulder Bag | G88: Curvy Mood Hobo Bag | H88: Black Quilted Calfskin Leather | I88: Aged Gold | L88: Yes | M88: Sold (full record)
A89: 21032763 | B89: Chanel | C89: Chanel CC Dice Tote Bag in Dark Chocolate Brown Grained Calfskin Leather and Light Gold Hardware Series 7 | D89: 88900 | E89: Chanel | F89: Tote | G89: CC Dice Tote Bag | H89: Dark Chocolate Brown Grained Calfskin Leather | I89: Light Gold | J89: Series 7 | M89: Not used
A90: 34837051 | B90: Chanel | C90: Chanel Classic Double Flap Small in Black Caviar Leather Gold Hardware (Series 31) | D90: 569000 | E90: Chanel | F90: Shoulder Bag | G90: Classic Double Flap Small | H90: Black Caviar Leather | I90: Gold | J90: Series 31 | M90: Not used
A91: 47779643 | B91: Chanel | C91: Chanel Classic Double Flap Medium in Black Caviar Leather and Gold Hardware Series 28 | D91: 485000 | E91: Chanel | F91: Shoulder Bag | G91: Classic Double Flap Medium | H91: Black Caviar Leather | I91: Gold | J91: Series 28 | M91: Sold (full record)
A92: 37490491 | B92: Chanel | C92: Chanel Fleur de Camelia in Light Gold Hardware Brooch | D92: 22000 | E92: Chanel | F92: Jewelry | G92: Fleur de Camelia | H92: Light | I92: Light Gold | M92: Historical sale (markup gap)
A93: 260961871 | B93: Chanel | C93: Chanel Strass Baguette Round Hoop Earrings | D93: 36600 | E93: Chanel | F93: Jewelry | G93: Strass Baguette Round Hoop Earrings | M93: Historical sale (markup gap)
A94: 70587195 | B94: Chanel | C94: Chanel Boy Old Medium in Salmon Pink Chevron Calfskin Leather and Aged Gold Hardware Series 28 | D94: 175600 | E94: Chanel | F94: Shoulder Bag | G94: Boy Old Medium | H94: Salmon Pink Chevron Calfskin Leather | I94: Aged Gold | J94: Series 28 | M94: Sold (full record)
A95: 54439227 | B95: Chanel | C95: Chanel Coco Lizard Handle Small in Dark Turquoise Quilted Caviar Leather and Aged Gold Hardware Series 28 | D95: 333800 | E95: Chanel | F95: Handbag | G95: Coco Lizard Handle Small | H95: Dark Turquoise Quilted Caviar Leather | I95: Aged Gold | J95: Series 28 | M95: Sold (full record)
A96: 2017155152 | B96: Chanel | C96: Chanel Mini Rectangular Top Handle Flap Bag in Black Lambskin Leather Light Gold Hardware (Microchip) | D96: 423400 | E96: Chanel | F96: Shoulder Bag | G96: Mini Rectangular Top Handle Flap Bag | H96: Black Lambskin Leather Light | I96: Light Gold | L96: Yes | M96: In stock – Available
A97: 81383483 | B97: Chanel | C97: Chanel CC Kelly Shopping Bag Small in Black Shiny Calfskin Leather Aged Gold Hardware (Microchip) | D97: 367400 | E97: Chanel | F97: Tote | G97: CC Kelly Shopping Bag Small | H97: Black Shiny Calfskin Leather Aged | I97: Aged Gold | L97: Yes | M97: Not used
A98: 39180603 | B98: Chanel | C98: Chanel Grand Shopping Tote in Beige Quilted Caviar Leather and Gold Hardware Series 16 | D98: 161800 | E98: Chanel | F98: Tote | G98: Grand Shopping Tote | H98: Beige Quilted Caviar Leather | I98: Gold | J98: Series 16 | M98: Not used
A99: 00067643 | B99: Chanel | C99: Chanel Classic Wallet on Chain (WOC) in Denim Fabric Canvas Light Gold (Microchip) | D99: 218300 | E99: Chanel | F99: Crossbody | G99: Classic Wallet on Chain | H99: Denim Fabric Canvas Light Gold | L99: Yes | M99: In stock – Available
A100: 86754107 | B100: Chanel | C100: Chanel Coco Handle Small in Black Caviar Leather and Gold Hardware Series 25 | D100: 333800 | E100: Chanel | F100: Handbag | G100: Coco Handle Small | H100: Black Caviar Leather | I100: Gold | J100: Series 25 | M100: In stock – Available
...
